{"id": "6OADNE5VKRM", "title": "Minecraft - Tutorial: 360 Cannon", "formats": [{"asr": 22050, "filesize": 17485936, "format_id": "139", "format_note": "low", "quality": 2, "tbr": 48.784, "url": "https://rr2---sn-ab5sznld.googlevideo.com/videoplayback?expire=1641451455&ei=XzvWYYG9L72P2LYPtuuV0Aw&ip=68.70.26.44&id=o-AG-JD-cUGc6gTEYW_rNJ684PpL-oj-PJNnz6y2nk317U&itag=139&source=youtube&requiressl=yes&mh=QR&mm=31%2C26&mn=sn-ab5sznld%2Csn-p5qlsnrl&ms=au%2Conr&mv=m&mvi=2&pl=20&initcwndbps=2248750&vprv=1&mime=audio%2Fmp4&gir=yes&clen=17485936&dur=2867.478&lmt=1568852322592000&mt=1641429661&fvip=2&keepalive=yes&fexp=24001373%2C24007246&c=ANDROID&txp=1311222&sparams=expire%2Cei%2Cip%2Cid%2Citag%2Csource%2Crequiressl%2Cvprv%2Cmime%2Cgir%2Cclen%2Cdur%2Clmt&sig=AOq0QJ8wRgIhANgOTQ8_F0Y-KcKrWpL55jUxey8GvuAa9wa5G5wE_gUpAiEA3n6mzxIq4kK9PLurWOWdFN5qcYxC1tNlvzaaVGKipaY%3D&lsparams=mh%2Cmm%2Cmn%2Cms%2Cmv%2Cmvi%2Cpl%2Cinitcwndbps&lsig=AG3C_xAwRQIgdSr9lkU7lcCXcnHfMsxexE6cJpGI8p0MhYIlWG4ziE0CIQCE7Ol6mDk0-l2bFpfX36I5Iqd5h5GF5FBntUr0EmoznQ%3D%3D", "language": "", "language_preference": -1, "ext": "m4a", "vcodec": "none", "acodec": "mp4a.40.5", "abr": 48.784, "downloader_options": {"http_chunk_size": 10485760}, "container": "m4a_dash", "protocol": "https", "audio_ext": "m4a", "video_ext": "none", "format": "139 - audio only (low)", "http_headers": {"User-Agent": "Mozilla/5.0 (Windows NT 10.0; Win64; x64) AppleWebKit/537.36 (KHTML, like Gecko) Chrome/74.0.3718.8 Safari/537.36", "Accept-Charset": "ISO-8859-1,utf-8;q=0.7,*;q=0.7", "Accept": "text/html,application/xhtml+xml,application/xml;q=0.9,*/*;q=0.8", "Accept-Encoding": "gzip, deflate", "Accept-Language": "en-us,en;q=0.5"}}, {"asr": 48000, "filesize": 17813333, "format_id": "249", "format_note": "low", "quality": 2, "tbr": 49.698, "url": "https://rr2---sn-ab5sznld.googlevideo.com/videoplayback?expire=1641451455&ei=XzvWYYG9L72P2LYPtuuV0Aw&ip=68.70.26.44&id=o-AG-JD-cUGc6gTEYW_rNJ684PpL-oj-PJNnz6y2nk317U&itag=249&source=youtube&requiressl=yes&mh=QR&mm=31%2C26&mn=sn-ab5sznld%2Csn-p5qlsnrl&ms=au%2Conr&mv=m&mvi=2&pl=20&initcwndbps=2248750&vprv=1&mime=audio%2Fwebm&gir=yes&clen=17813333&dur=2867.401&lmt=1568853357602761&mt=1641429661&fvip=2&keepalive=yes&fexp=24001373%2C24007246&c=ANDROID&txp=1301222&sparams=expire%2Cei%2Cip%2Cid%2Citag%2Csource%2Crequiressl%2Cvprv%2Cmime%2Cgir%2Cclen%2Cdur%2Clmt&sig=AOq0QJ8wRQIgBa-9tPhTvJah0sgnygE5xdrf-oLARZ-L3AvdLydpcpACIQCHljaCNko0SDun2rCqv03YxjNIqcnBUxvwAvM3dXEKBQ%3D%3D&lsparams=mh%2Cmm%2Cmn%2Cms%2Cmv%2Cmvi%2Cpl%2Cinitcwndbps&lsig=AG3C_xAwRQIgdSr9lkU7lcCXcnHfMsxexE6cJpGI8p0MhYIlWG4ziE0CIQCE7Ol6mDk0-l2bFpfX36I5Iqd5h5GF5FBntUr0EmoznQ%3D%3D", "language": "", "language_preference": -1, "ext": "webm", "vcodec": "none", "acodec": "opus", "abr": 49.698, "downloader_options": {"http_chunk_size": 10485760}, "container": "webm_dash", "protocol": "https", "audio_ext": "webm", "video_ext": "none", "format": "249 - audio only (low)", "http_headers": {"User-Agent": "Mozilla/5.0 (Windows NT 10.0; Win64; x64) AppleWebKit/537.36 (KHTML, like Gecko) Chrome/74.0.3718.8 Safari/537.36", "Accept-Charset": "ISO-8859-1,utf-8;q=0.7,*;q=0.7", "Accept": "text/html,application/xhtml+xml,application/xml;q=0.9,*/*;q=0.8", "Accept-Encoding": "gzip, deflate", "Accept-Language": "en-us,en;q=0.5"}}, {"asr": 48000, "filesize": 20577433, "format_id": "250", "format_note": "low", "quality": 2, "tbr": 57.41, "url": "https://rr2---sn-ab5sznld.googlevideo.com/videoplayback?expire=1641451455&ei=XzvWYYG9L72P2LYPtuuV0Aw&ip=68.70.26.44&id=o-AG-JD-cUGc6gTEYW_rNJ684PpL-oj-PJNnz6y2nk317U&itag=250&source=youtube&requiressl=yes&mh=QR&mm=31%2C26&mn=sn-ab5sznld%2Csn-p5qlsnrl&ms=au%2Conr&mv=m&mvi=2&pl=20&initcwndbps=2248750&vprv=1&mime=audio%2Fwebm&gir=yes&clen=20577433&dur=2867.401&lmt=1568853296636455&mt=1641429661&fvip=2&keepalive=yes&fexp=24001373%2C24007246&c=ANDROID&txp=1301222&sparams=expire%2Cei%2Cip%2Cid%2Citag%2Csource%2Crequiressl%2Cvprv%2Cmime%2Cgir%2Cclen%2Cdur%2Clmt&sig=AOq0QJ8wRQIhAI2DNgwvFfyi_HwAlyeI__8o4QjlxEaLCJGSlitPWyrPAiAmUxr8VJa9wPn2SC2FXoX0QBbAJhqh9r_unAY7t6FjTg%3D%3D&lsparams=mh%2Cmm%2Cmn%2Cms%2Cmv%2Cmvi%2Cpl%2Cinitcwndbps&lsig=AG3C_xAwRQIgdSr9lkU7lcCXcnHfMsxexE6cJpGI8p0MhYIlWG4ziE0CIQCE7Ol6mDk0-l2bFpfX36I5Iqd5h5GF5FBntUr0EmoznQ%3D%3D", "language": "", "language_preference": -1, "ext": "webm", "vcodec": "none", "acodec": "opus", "abr": 57.41, "downloader_options": {"http_chunk_size": 10485760}, "container": "webm_dash", "protocol": "https", "audio_ext": "webm", "video_ext": "none", "format": "250 - audio only (low)", "http_headers": {"User-Agent": "Mozilla/5.0 (Windows NT 10.0; Win64; x64) AppleWebKit/537.36 (KHTML, like Gecko) Chrome/74.0.3718.8 Safari/537.36", "Accept-Charset": "ISO-8859-1,utf-8;q=0.7,*;q=0.7", "Accept": "text/html,application/xhtml+xml,application/xml;q=0.9,*/*;q=0.8", "Accept-Encoding": "gzip, deflate", "Accept-Language": "en-us,en;q=0.5"}}, {"asr": 44100, "filesize": 46406947, "format_id": "140", "format_note": "medium", "quality": 3, "tbr": 129.473, "url": "https://rr2---sn-ab5sznld.googlevideo.com/videoplayback?expire=1641451455&ei=XzvWYYG9L72P2LYPtuuV0Aw&ip=68.70.26.44&id=o-AG-JD-cUGc6gTEYW_rNJ684PpL-oj-PJNnz6y2nk317U&itag=140&source=youtube&requiressl=yes&mh=QR&mm=31%2C26&mn=sn-ab5sznld%2Csn-p5qlsnrl&ms=au%2Conr&mv=m&mvi=2&pl=20&initcwndbps=2248750&vprv=1&mime=audio%2Fmp4&gir=yes&clen=46406947&dur=2867.432&lmt=1568852296587042&mt=1641429661&fvip=2&keepalive=yes&fexp=24001373%2C24007246&c=ANDROID&txp=1311222&sparams=expire%2Cei%2Cip%2Cid%2Citag%2Csource%2Crequiressl%2Cvprv%2Cmime%2Cgir%2Cclen%2Cdur%2Clmt&sig=AOq0QJ8wRQIgRYaChoHSEZicfqmh0MBZ8XhwXSTjBPY-wpjbQiL68p0CIQDA6IB5TszaxtA-eRlP5NcaJsYYmqcAP_9hSDwuXJ11vA%3D%3D&lsparams=mh%2Cmm%2Cmn%2Cms%2Cmv%2Cmvi%2Cpl%2Cinitcwndbps&lsig=AG3C_xAwRQIgdSr9lkU7lcCXcnHfMsxexE6cJpGI8p0MhYIlWG4ziE0CIQCE7Ol6mDk0-l2bFpfX36I5Iqd5h5GF5FBntUr0EmoznQ%3D%3D", "language": "", "language_preference": -1, "ext": "m4a", "vcodec": "none", "acodec": "mp4a.40.2", "abr": 129.473, "downloader_options": {"http_chunk_size": 10485760}, "container": "m4a_dash", "protocol": "https", "audio_ext": "m4a", "video_ext": "none", "format": "140 - audio only (medium)", "http_headers": {"User-Agent": "Mozilla/5.0 (Windows NT 10.0; Win64; x64) AppleWebKit/537.36 (KHTML, like Gecko) Chrome/74.0.3718.8 Safari/537.36", "Accept-Charset": "ISO-8859-1,utf-8;q=0.7,*;q=0.7", "Accept": "text/html,application/xhtml+xml,application/xml;q=0.9,*/*;q=0.8", "Accept-Encoding": "gzip, deflate", "Accept-Language": "en-us,en;q=0.5"}}, {"asr": 48000, "filesize": 37882298, "format_id": "251", "format_note": "medium", "quality": 3, "tbr": 105.69, "url": "https://rr2---sn-ab5sznld.googlevideo.com/videoplayback?expire=1641451455&ei=XzvWYYG9L72P2LYPtuuV0Aw&ip=68.70.26.44&id=o-AG-JD-cUGc6gTEYW_rNJ684PpL-oj-PJNnz6y2nk317U&itag=251&source=youtube&requiressl=yes&mh=QR&mm=31%2C26&mn=sn-ab5sznld%2Csn-p5qlsnrl&ms=au%2Conr&mv=m&mvi=2&pl=20&initcwndbps=2248750&vprv=1&mime=audio%2Fwebm&gir=yes&clen=37882298&dur=2867.401&lmt=1568853293523724&mt=1641429661&fvip=2&keepalive=yes&fexp=24001373%2C24007246&c=ANDROID&txp=1301222&sparams=expire%2Cei%2Cip%2Cid%2Citag%2Csource%2Crequiressl%2Cvprv%2Cmime%2Cgir%2Cclen%2Cdur%2Clmt&sig=AOq0QJ8wRQIhANg3aRKbOLzrw5WofcaGs9wjvJEw3WQOhsyiQc56yHffAiBIsmPgZZ6YyBGjUIP44rbFxhq9fMkl2hukOwktJnk8lw%3D%3D&lsparams=mh%2Cmm%2Cmn%2Cms%2Cmv%2Cmvi%2Cpl%2Cinitcwndbps&lsig=AG3C_xAwRQIgdSr9lkU7lcCXcnHfMsxexE6cJpGI8p0MhYIlWG4ziE0CIQCE7Ol6mDk0-l2bFpfX36I5Iqd5h5GF5FBntUr0EmoznQ%3D%3D", "language": "", "language_preference": -1, "ext": "webm", "vcodec": "none", "acodec": "opus", "abr": 105.69, "downloader_options": {"http_chunk_size": 10485760}, "container": "webm_dash", "protocol": "https", "audio_ext": "webm", "video_ext": "none", "format": "251 - audio only (medium)", "http_headers": {"User-Agent": "Mozilla/5.0 (Windows NT 10.0; Win64; x64) AppleWebKit/537.36 (KHTML, like Gecko) Chrome/74.0.3718.8 Safari/537.36", "Accept-Charset": "ISO-8859-1,utf-8;q=0.7,*;q=0.7", "Accept": "text/html,application/xhtml+xml,application/xml;q=0.9,*/*;q=0.8", "Accept-Encoding": "gzip, deflate", "Accept-Language": "en-us,en;q=0.5"}}, {"asr": 22050, "filesize": 28641051, "format_id": "17", "format_note": "144p", "fps": 8, "height": 144, "quality": 0, "tbr": 79.905, "url": "https://rr2---sn-ab5sznld.googlevideo.com/videoplayback?expire=1641451455&ei=XzvWYYG9L72P2LYPtuuV0Aw&ip=68.70.26.44&id=o-AG-JD-cUGc6gTEYW_rNJ684PpL-oj-PJNnz6y2nk317U&itag=17&source=youtube&requiressl=yes&mh=QR&mm=31%2C26&mn=sn-ab5sznld%2Csn-p5qlsnrl&ms=au%2Conr&mv=m&mvi=2&pl=20&initcwndbps=2248750&vprv=1&mime=video%2F3gpp&gir=yes&clen=28641051&dur=2867.478&lmt=1568852434364874&mt=1641429661&fvip=2&fexp=24001373%2C24007246&c=ANDROID&txp=1311222&sparams=expire%2Cei%2Cip%2Cid%2Citag%2Csource%2Crequiressl%2Cvprv%2Cmime%2Cgir%2Cclen%2Cdur%2Clmt&sig=AOq0QJ8wRgIhAOFZsGHjZ2CekVI-3ZOdY0A8vU2muSTQPvnt7cWSvBFlAiEAxraeIn57MdH54mqnPwPhF5R2Bh7ywgO6Aait6JkscNQ%3D&lsparams=mh%2Cmm%2Cmn%2Cms%2Cmv%2Cmvi%2Cpl%2Cinitcwndbps&lsig=AG3C_xAwRQIgdSr9lkU7lcCXcnHfMsxexE6cJpGI8p0MhYIlWG4ziE0CIQCE7Ol6mDk0-l2bFpfX36I5Iqd5h5GF5FBntUr0EmoznQ%3D%3D", "width": 176, "language": "", "language_preference": -1, "ext": "3gp", "vcodec": "mp4v.20.3", "acodec": "mp4a.40.2", "protocol": "https", "video_ext": "3gp", "audio_ext": "none", "vbr": 79.905, "abr": 0.0, "format": "17 - 176x144 (144p)", "http_headers": {"User-Agent": "Mozilla/5.0 (Windows NT 10.0; Win64; x64) AppleWebKit/537.36 (KHTML, like Gecko) Chrome/74.0.3718.8 Safari/537.36", "Accept-Charset": "ISO-8859-1,utf-8;q=0.7,*;q=0.7", "Accept": "text/html,application/xhtml+xml,application/xml;q=0.9,*/*;q=0.8", "Accept-Encoding": "gzip, deflate", "Accept-Language": "en-us,en;q=0.5"}}, {"filesize": 36212243, "format_id": "160", "format_note": "144p", "fps": 30, "height": 144, "quality": 0, "tbr": 101.032, "url": "https://rr2---sn-ab5sznld.googlevideo.com/videoplayback?expire=1641451455&ei=XzvWYYG9L72P2LYPtuuV0Aw&ip=68.70.26.44&id=o-AG-JD-cUGc6gTEYW_rNJ684PpL-oj-PJNnz6y2nk317U&itag=160&source=youtube&requiressl=yes&mh=QR&mm=31%2C26&mn=sn-ab5sznld%2Csn-p5qlsnrl&ms=au%2Conr&mv=m&mvi=2&pl=20&initcwndbps=2248750&vprv=1&mime=video%2Fmp4&gir=yes&clen=36212243&dur=2867.366&lmt=1568852397415358&mt=1641429661&fvip=2&keepalive=yes&fexp=24001373%2C24007246&c=ANDROID&txp=1311222&sparams=expire%2Cei%2Cip%2Cid%2Citag%2Csource%2Crequiressl%2Cvprv%2Cmime%2Cgir%2Cclen%2Cdur%2Clmt&sig=AOq0QJ8wRQIhAIayoGHkc23U3Ko8pxyGL1ibVF37BPg_1xwa7s23_cxBAiAFocfgVvUBl8EddOOas1RCxoBLHLFSYGfJ4u0e0huMyw%3D%3D&lsparams=mh%2Cmm%2Cmn%2Cms%2Cmv%2Cmvi%2Cpl%2Cinitcwndbps&lsig=AG3C_xAwRQIgdSr9lkU7lcCXcnHfMsxexE6cJpGI8p0MhYIlWG4ziE0CIQCE7Ol6mDk0-l2bFpfX36I5Iqd5h5GF5FBntUr0EmoznQ%3D%3D", "width": 256, "language": "", "language_preference": -1, "ext": "mp4", "vcodec": "avc1.4d400c", "acodec": "none", "vbr": 101.032, "downloader_options": {"http_chunk_size": 10485760}, "container": "mp4_dash", "protocol": "https", "video_ext": "mp4", "audio_ext": "none", "format": "160 - 256x144 (144p)", "http_headers": {"User-Agent": "Mozilla/5.0 (Windows NT 10.0; Win64; x64) AppleWebKit/537.36 (KHTML, like Gecko) Chrome/74.0.3718.8 Safari/537.36", "Accept-Charset": "ISO-8859-1,utf-8;q=0.7,*;q=0.7", "Accept": "text/html,application/xhtml+xml,application/xml;q=0.9,*/*;q=0.8", "Accept-Encoding": "gzip, deflate", "Accept-Language": "en-us,en;q=0.5"}}, {"filesize": 32106128, "format_id": "278", "format_note": "144p", "fps": 30, "height": 144, "quality": 0, "tbr": 89.576, "url": "https://rr2---sn-ab5sznld.googlevideo.com/videoplayback?expire=1641451455&ei=XzvWYYG9L72P2LYPtuuV0Aw&ip=68.70.26.44&id=o-AG-JD-cUGc6gTEYW_rNJ684PpL-oj-PJNnz6y2nk317U&itag=278&source=youtube&requiressl=yes&mh=QR&mm=31%2C26&mn=sn-ab5sznld%2Csn-p5qlsnrl&ms=au%2Conr&mv=m&mvi=2&pl=20&initcwndbps=2248750&vprv=1&mime=video%2Fwebm&gir=yes&clen=32106128&dur=2867.366&lmt=1568855681156982&mt=1641429661&fvip=2&keepalive=yes&fexp=24001373%2C24007246&c=ANDROID&txp=1301222&sparams=expire%2Cei%2Cip%2Cid%2Citag%2Csource%2Crequiressl%2Cvprv%2Cmime%2Cgir%2Cclen%2Cdur%2Clmt&sig=AOq0QJ8wRgIhANImycav0NdqnK90QdVv78vJp6EkGuh3kCxEMmQkUEF5AiEAmNlaQz-aTO1WO6ol4s-o8q3CsO_f2w_KnGac9CTN_Bo%3D&lsparams=mh%2Cmm%2Cmn%2Cms%2Cmv%2Cmvi%2Cpl%2Cinitcwndbps&lsig=AG3C_xAwRQIgdSr9lkU7lcCXcnHfMsxexE6cJpGI8p0MhYIlWG4ziE0CIQCE7Ol6mDk0-l2bFpfX36I5Iqd5h5GF5FBntUr0EmoznQ%3D%3D", "width": 256, "language": "", "language_preference": -1, "ext": "webm", "vcodec": "vp9", "acodec": "none", "vbr": 89.576, "downloader_options": {"http_chunk_size": 10485760}, "container": "webm_dash", "protocol": "https", "video_ext": "webm", "audio_ext": "none", "format": "278 - 256x144 (144p)", "http_headers": {"User-Agent": "Mozilla/5.0 (Windows NT 10.0; Win64; x64) AppleWebKit/537.36 (KHTML, like Gecko) Chrome/74.0.3718.8 Safari/537.36", "Accept-Charset": "ISO-8859-1,utf-8;q=0.7,*;q=0.7", "Accept": "text/html,application/xhtml+xml,application/xml;q=0.9,*/*;q=0.8", "Accept-Encoding": "gzip, deflate", "Accept-Language": "en-us,en;q=0.5"}}, {"filesize": 79901201, "format_id": "133", "format_note": "240p", "fps": 30, "height": 240, "quality": 5, "tbr": 222.925, "url": "https://rr2---sn-ab5sznld.googlevideo.com/videoplayback?expire=1641451455&ei=XzvWYYG9L72P2LYPtuuV0Aw&ip=68.70.26.44&id=o-AG-JD-cUGc6gTEYW_rNJ684PpL-oj-PJNnz6y2nk317U&itag=133&source=youtube&requiressl=yes&mh=QR&mm=31%2C26&mn=sn-ab5sznld%2Csn-p5qlsnrl&ms=au%2Conr&mv=m&mvi=2&pl=20&initcwndbps=2248750&vprv=1&mime=video%2Fmp4&gir=yes&clen=79901201&dur=2867.366&lmt=1568852397412603&mt=1641429661&fvip=2&keepalive=yes&fexp=24001373%2C24007246&c=ANDROID&txp=1311222&sparams=expire%2Cei%2Cip%2Cid%2Citag%2Csource%2Crequiressl%2Cvprv%2Cmime%2Cgir%2Cclen%2Cdur%2Clmt&sig=AOq0QJ8wRgIhAM3gk5rMLWuKRCvOLAlfsAtEKGxw5tepYZV97y34QS9MAiEA8Zhnx9cYvKVoAJCFsMjF1ggEG_L43yFJrdK6aFY0b0Q%3D&lsparams=mh%2Cmm%2Cmn%2Cms%2Cmv%2Cmvi%2Cpl%2Cinitcwndbps&lsig=AG3C_xAwRQIgdSr9lkU7lcCXcnHfMsxexE6cJpGI8p0MhYIlWG4ziE0CIQCE7Ol6mDk0-l2bFpfX36I5Iqd5h5GF5FBntUr0EmoznQ%3D%3D", "width": 426, "language": "", "language_preference": -1, "ext": "mp4", "vcodec": "avc1.4d4015", "acodec": "none", "vbr": 222.925, "downloader_options": {"http_chunk_size": 10485760}, "container": "mp4_dash", "protocol": "https", "video_ext": "mp4", "audio_ext": "none", "format": "133 - 426x240 (240p)", "http_headers": {"User-Agent": "Mozilla/5.0 (Windows NT 10.0; Win64; x64) AppleWebKit/537.36 (KHTML, like Gecko) Chrome/74.0.3718.8 Safari/537.36", "Accept-Charset": "ISO-8859-1,utf-8;q=0.7,*;q=0.7", "Accept": "text/html,application/xhtml+xml,application/xml;q=0.9,*/*;q=0.8", "Accept-Encoding": "gzip, deflate", "Accept-Language": "en-us,en;q=0.5"}}, {"filesize": 68534666, "format_id": "242", "format_note": "240p", "fps": 30, "height": 240, "quality": 5, "tbr": 191.212, "url": "https://rr2---sn-ab5sznld.googlevideo.com/videoplayback?expire=1641451455&ei=XzvWYYG9L72P2LYPtuuV0Aw&ip=68.70.26.44&id=o-AG-JD-cUGc6gTEYW_rNJ684PpL-oj-PJNnz6y2nk317U&itag=242&source=youtube&requiressl=yes&mh=QR&mm=31%2C26&mn=sn-ab5sznld%2Csn-p5qlsnrl&ms=au%2Conr&mv=m&mvi=2&pl=20&initcwndbps=2248750&vprv=1&mime=video%2Fwebm&gir=yes&clen=68534666&dur=2867.366&lmt=1568855681164313&mt=1641429661&fvip=2&keepalive=yes&fexp=24001373%2C24007246&c=ANDROID&txp=1301222&sparams=expire%2Cei%2Cip%2Cid%2Citag%2Csource%2Crequiressl%2Cvprv%2Cmime%2Cgir%2Cclen%2Cdur%2Clmt&sig=AOq0QJ8wRQIgRcPQuzhcju_p7iDzx3a1_QVMUmFrYEgVR7OQLnhiXaQCIQC-54whXYrZSFCi6RPvKxv0yaNsFNYxmbSyYoCr2C_c9g%3D%3D&lsparams=mh%2Cmm%2Cmn%2Cms%2Cmv%2Cmvi%2Cpl%2Cinitcwndbps&lsig=AG3C_xAwRQIgdSr9lkU7lcCXcnHfMsxexE6cJpGI8p0MhYIlWG4ziE0CIQCE7Ol6mDk0-l2bFpfX36I5Iqd5h5GF5FBntUr0EmoznQ%3D%3D", "width": 426, "language": "", "language_preference": -1, "ext": "webm", "vcodec": "vp9", "acodec": "none", "vbr": 191.212, "downloader_options": {"http_chunk_size": 10485760}, "container": "webm_dash", "protocol": "https", "video_ext": "webm", "audio_ext": "none", "format": "242 - 426x240 (240p)", "http_headers": {"User-Agent": "Mozilla/5.0 (Windows NT 10.0; Win64; x64) AppleWebKit/537.36 (KHTML, like Gecko) Chrome/74.0.3718.8 Safari/537.36", "Accept-Charset": "ISO-8859-1,utf-8;q=0.7,*;q=0.7", "Accept": "text/html,application/xhtml+xml,application/xml;q=0.9,*/*;q=0.8", "Accept-Encoding": "gzip, deflate", "Accept-Language": "en-us,en;q=0.5"}}, {"filesize": 174499823, "format_id": "134", "format_note": "360p", "fps": 30, "height": 360, "quality": 6, "tbr": 486.857, "url": "https://rr2---sn-ab5sznld.googlevideo.com/videoplayback?expire=1641451455&ei=XzvWYYG9L72P2LYPtuuV0Aw&ip=68.70.26.44&id=o-AG-JD-cUGc6gTEYW_rNJ684PpL-oj-PJNnz6y2nk317U&itag=134&source=youtube&requiressl=yes&mh=QR&mm=31%2C26&mn=sn-ab5sznld%2Csn-p5qlsnrl&ms=au%2Conr&mv=m&mvi=2&pl=20&initcwndbps=2248750&vprv=1&mime=video%2Fmp4&gir=yes&clen=174499823&dur=2867.366&lmt=1568852397416956&mt=1641429661&fvip=2&keepalive=yes&fexp=24001373%2C24007246&c=ANDROID&txp=1311222&sparams=expire%2Cei%2Cip%2Cid%2Citag%2Csource%2Crequiressl%2Cvprv%2Cmime%2Cgir%2Cclen%2Cdur%2Clmt&sig=AOq0QJ8wRQIgDUKu0DKeydlXU9SegZ7xVEqMlGbUqDMpfMMpe_7mVcQCIQDRbhaL_93vZf1GBnW-2LA_nXdsv3yCbpc1PTtEUohrkg%3D%3D&lsparams=mh%2Cmm%2Cmn%2Cms%2Cmv%2Cmvi%2Cpl%2Cinitcwndbps&lsig=AG3C_xAwRQIgdSr9lkU7lcCXcnHfMsxexE6cJpGI8p0MhYIlWG4ziE0CIQCE7Ol6mDk0-l2bFpfX36I5Iqd5h5GF5FBntUr0EmoznQ%3D%3D", "width": 640, "language": "", "language_preference": -1, "ext": "mp4", "vcodec": "avc1.4d401e", "acodec": "none", "vbr": 486.857, "downloader_options": {"http_chunk_size": 10485760}, "container": "mp4_dash", "protocol": "https", "video_ext": "mp4", "audio_ext": "none", "format": "134 - 640x360 (360p)", "http_headers": {"User-Agent": "Mozilla/5.0 (Windows NT 10.0; Win64; x64) AppleWebKit/537.36 (KHTML, like Gecko) Chrome/74.0.3718.8 Safari/537.36", "Accept-Charset": "ISO-8859-1,utf-8;q=0.7,*;q=0.7", "Accept": "text/html,application/xhtml+xml,application/xml;q=0.9,*/*;q=0.8", "Accept-Encoding": "gzip, deflate", "Accept-Language": "en-us,en;q=0.5"}}, {"asr": 44100, "filesize": 235895564, "format_id": "18", "format_note": "360p", "fps": 30, "height": 360, "quality": 6, "tbr": 658.137, "url": "https://rr2---sn-ab5sznld.googlevideo.com/videoplayback?expire=1641451455&ei=XzvWYYG9L72P2LYPtuuV0Aw&ip=68.70.26.44&id=o-AG-JD-cUGc6gTEYW_rNJ684PpL-oj-PJNnz6y2nk317U&itag=18&source=youtube&requiressl=yes&mh=QR&mm=31%2C26&mn=sn-ab5sznld%2Csn-p5qlsnrl&ms=au%2Conr&mv=m&mvi=2&pl=20&initcwndbps=2248750&vprv=1&mime=video%2Fmp4&gir=yes&clen=235895564&ratebypass=yes&dur=2867.432&lmt=1568852551743823&mt=1641429661&fvip=2&fexp=24001373%2C24007246&c=ANDROID&txp=1311222&sparams=expire%2Cei%2Cip%2Cid%2Citag%2Csource%2Crequiressl%2Cvprv%2Cmime%2Cgir%2Cclen%2Cratebypass%2Cdur%2Clmt&sig=AOq0QJ8wRgIhANv-NBGZEcxoK1gfg20ed7ZCQOMWrmpnjTYmwhN9uKTxAiEAzMTwrKoOx8Y2veM4D5ZPChXtsAAkkq86BHwBoc-y3sU%3D&lsparams=mh%2Cmm%2Cmn%2Cms%2Cmv%2Cmvi%2Cpl%2Cinitcwndbps&lsig=AG3C_xAwRQIgdSr9lkU7lcCXcnHfMsxexE6cJpGI8p0MhYIlWG4ziE0CIQCE7Ol6mDk0-l2bFpfX36I5Iqd5h5GF5FBntUr0EmoznQ%3D%3D", "width": 640, "language": "", "language_preference": -1, "ext": "mp4", "vcodec": "avc1.42001E", "acodec": "mp4a.40.2", "protocol": "https", "video_ext": "mp4", "audio_ext": "none", "vbr": 658.137, "abr": 0.0, "format": "18 - 640x360 (360p)", "http_headers": {"User-Agent": "Mozilla/5.0 (Windows NT 10.0; Win64; x64) AppleWebKit/537.36 (KHTML, like Gecko) Chrome/74.0.3718.8 Safari/537.36", "Accept-Charset": "ISO-8859-1,utf-8;q=0.7,*;q=0.7", "Accept": "text/html,application/xhtml+xml,application/xml;q=0.9,*/*;q=0.8", "Accept-Encoding": "gzip, deflate", "Accept-Language": "en-us,en;q=0.5"}}, {"filesize": 125497410, "format_id": "243", "format_note": "360p", "fps": 30, "height": 360, "quality": 6, "tbr": 350.139, "url": "https://rr2---sn-ab5sznld.googlevideo.com/videoplayback?expire=1641451455&ei=XzvWYYG9L72P2LYPtuuV0Aw&ip=68.70.26.44&id=o-AG-JD-cUGc6gTEYW_rNJ684PpL-oj-PJNnz6y2nk317U&itag=243&source=youtube&requiressl=yes&mh=QR&mm=31%2C26&mn=sn-ab5sznld%2Csn-p5qlsnrl&ms=au%2Conr&mv=m&mvi=2&pl=20&initcwndbps=2248750&vprv=1&mime=video%2Fwebm&gir=yes&clen=125497410&dur=2867.366&lmt=1568855681162328&mt=1641429661&fvip=2&keepalive=yes&fexp=24001373%2C24007246&c=ANDROID&txp=1301222&sparams=expire%2Cei%2Cip%2Cid%2Citag%2Csource%2Crequiressl%2Cvprv%2Cmime%2Cgir%2Cclen%2Cdur%2Clmt&sig=AOq0QJ8wRQIgF4falOGv6yO0Igrtm1aXpdmHeFbeLB0-ncsJgNDa_9kCIQDD7NyMWZgr2DQRegiCjcysXcR10sE94xgNR3rzXxPg8Q%3D%3D&lsparams=mh%2Cmm%2Cmn%2Cms%2Cmv%2Cmvi%2Cpl%2Cinitcwndbps&lsig=AG3C_xAwRQIgdSr9lkU7lcCXcnHfMsxexE6cJpGI8p0MhYIlWG4ziE0CIQCE7Ol6mDk0-l2bFpfX36I5Iqd5h5GF5FBntUr0EmoznQ%3D%3D", "width": 640, "language": "", "language_preference": -1, "ext": "webm", "vcodec": "vp9", "acodec": "none", "vbr": 350.139, "downloader_options": {"http_chunk_size": 10485760}, "container": "webm_dash", "protocol": "https", "video_ext": "webm", "audio_ext": "none", "format": "243 - 640x360 (360p)", "http_headers": {"User-Agent": "Mozilla/5.0 (Windows NT 10.0; Win64; x64) AppleWebKit/537.36 (KHTML, like Gecko) Chrome/74.0.3718.8 Safari/537.36", "Accept-Charset": "ISO-8859-1,utf-8;q=0.7,*;q=0.7", "Accept": "text/html,application/xhtml+xml,application/xml;q=0.9,*/*;q=0.8", "Accept-Encoding": "gzip, deflate", "Accept-Language": "en-us,en;q=0.5"}}, {"filesize": 342957452, "format_id": "135", "format_note": "480p", "fps": 30, "height": 480, "quality": 7, "tbr": 956.857, "url": "https://rr2---sn-ab5sznld.googlevideo.com/videoplayback?expire=1641451455&ei=XzvWYYG9L72P2LYPtuuV0Aw&ip=68.70.26.44&id=o-AG-JD-cUGc6gTEYW_rNJ684PpL-oj-PJNnz6y2nk317U&itag=135&source=youtube&requiressl=yes&mh=QR&mm=31%2C26&mn=sn-ab5sznld%2Csn-p5qlsnrl&ms=au%2Conr&mv=m&mvi=2&pl=20&initcwndbps=2248750&vprv=1&mime=video%2Fmp4&gir=yes&clen=342957452&dur=2867.366&lmt=1568852397415698&mt=1641429661&fvip=2&keepalive=yes&fexp=24001373%2C24007246&c=ANDROID&txp=1311222&sparams=expire%2Cei%2Cip%2Cid%2Citag%2Csource%2Crequiressl%2Cvprv%2Cmime%2Cgir%2Cclen%2Cdur%2Clmt&sig=AOq0QJ8wRgIhAJ7C5VesTYZRrdDUVLaScPZwk1FczM1_MSNnHLHNXtdJAiEAuI5RBoPUbX6hJkdwskxG2nbB9wmMC_EpsCVkoZFY2hg%3D&lsparams=mh%2Cmm%2Cmn%2Cms%2Cmv%2Cmvi%2Cpl%2Cinitcwndbps&lsig=AG3C_xAwRQIgdSr9lkU7lcCXcnHfMsxexE6cJpGI8p0MhYIlWG4ziE0CIQCE7Ol6mDk0-l2bFpfX36I5Iqd5h5GF5FBntUr0EmoznQ%3D%3D", "width": 854, "language": "", "language_preference": -1, "ext": "mp4", "vcodec": "avc1.4d401f", "acodec": "none", "vbr": 956.857, "downloader_options": {"http_chunk_size": 10485760}, "container": "mp4_dash", "protocol": "https", "video_ext": "mp4", "audio_ext": "none", "format": "135 - 854x480 (480p)", "http_headers": {"User-Agent": "Mozilla/5.0 (Windows NT 10.0; Win64; x64) AppleWebKit/537.36 (KHTML, like Gecko) Chrome/74.0.3718.8 Safari/537.36", "Accept-Charset": "ISO-8859-1,utf-8;q=0.7,*;q=0.7", "Accept": "text/html,application/xhtml+xml,application/xml;q=0.9,*/*;q=0.8", "Accept-Encoding": "gzip, deflate", "Accept-Language": "en-us,en;q=0.5"}}, {"filesize": 234093757, "format_id": "244", "format_note": "480p", "fps": 30, "height": 480, "quality": 7, "tbr": 653.125, "url": "https://rr2---sn-ab5sznld.googlevideo.com/videoplayback?expire=1641451455&ei=XzvWYYG9L72P2LYPtuuV0Aw&ip=68.70.26.44&id=o-AG-JD-cUGc6gTEYW_rNJ684PpL-oj-PJNnz6y2nk317U&itag=244&source=youtube&requiressl=yes&mh=QR&mm=31%2C26&mn=sn-ab5sznld%2Csn-p5qlsnrl&ms=au%2Conr&mv=m&mvi=2&pl=20&initcwndbps=2248750&vprv=1&mime=video%2Fwebm&gir=yes&clen=234093757&dur=2867.366&lmt=1568855681151870&mt=1641429661&fvip=2&keepalive=yes&fexp=24001373%2C24007246&c=ANDROID&txp=1301222&sparams=expire%2Cei%2Cip%2Cid%2Citag%2Csource%2Crequiressl%2Cvprv%2Cmime%2Cgir%2Cclen%2Cdur%2Clmt&sig=AOq0QJ8wRQIgdrjrGmLay8yfokeMLWmYlLxNFjyjvjPHq2oN9vbYxvACIQDV3jKlp3g-plY3PijBAyktmv1WuCbm7f0prqryJc2d2Q%3D%3D&lsparams=mh%2Cmm%2Cmn%2Cms%2Cmv%2Cmvi%2Cpl%2Cinitcwndbps&lsig=AG3C_xAwRQIgdSr9lkU7lcCXcnHfMsxexE6cJpGI8p0MhYIlWG4ziE0CIQCE7Ol6mDk0-l2bFpfX36I5Iqd5h5GF5FBntUr0EmoznQ%3D%3D", "width": 854, "language": "", "language_preference": -1, "ext": "webm", "vcodec": "vp9", "acodec": "none", "vbr": 653.125, "downloader_options": {"http_chunk_size": 10485760}, "container": "webm_dash", "protocol": "https", "video_ext": "webm", "audio_ext": "none", "format": "244 - 854x480 (480p)", "http_headers": {"User-Agent": "Mozilla/5.0 (Windows NT 10.0; Win64; x64) AppleWebKit/537.36 (KHTML, like Gecko) Chrome/74.0.3718.8 Safari/537.36", "Accept-Charset": "ISO-8859-1,utf-8;q=0.7,*;q=0.7", "Accept": "text/html,application/xhtml+xml,application/xml;q=0.9,*/*;q=0.8", "Accept-Encoding": "gzip, deflate", "Accept-Language": "en-us,en;q=0.5"}}], "thumbnails": [{"url": "https://i.ytimg.com/vi/6OADNE5VKRM/3.jpg", "preference": -37, "id": "0"}, {"url": "https://i.ytimg.com/vi_webp/6OADNE5VKRM/3.webp", "preference": -36, "id": "1"}, {"url": "https://i.ytimg.com/vi/6OADNE5VKRM/2.jpg", "preference": -35, "id": "2"}, {"url": "https://i.ytimg.com/vi_webp/6OADNE5VKRM/2.webp", "preference": -34, "id": "3"}, {"url": "https://i.ytimg.com/vi/6OADNE5VKRM/1.jpg", "preference": -33, "id": "4"}, {"url": "https://i.ytimg.com/vi_webp/6OADNE5VKRM/1.webp", "preference": -32, "id": "5"}, {"url": "https://i.ytimg.com/vi/6OADNE5VKRM/default.jpg", "preference": -31, "id": "6"}, {"url": "https://i.ytimg.com/vi_webp/6OADNE5VKRM/default.webp", "height": 90, "width": 120, "preference": -30, "id": "7", "resolution": "120x90"}, {"url": "https://i.ytimg.com/vi/6OADNE5VKRM/mq3.jpg", "preference": -29, "id": "8"}, {"url": "https://i.ytimg.com/vi_webp/6OADNE5VKRM/mq3.webp", "preference": -28, "id": "9"}, {"url": "https://i.ytimg.com/vi/6OADNE5VKRM/mq2.jpg", "preference": -27, "id": "10"}, {"url": "https://i.ytimg.com/vi_webp/6OADNE5VKRM/mq2.webp", "preference": -26, "id": "11"}, {"url": "https://i.ytimg.com/vi/6OADNE5VKRM/mq1.jpg", "preference": -25, "id": "12"}, {"url": "https://i.ytimg.com/vi_webp/6OADNE5VKRM/mq1.webp", "preference": -24, "id": "13"}, {"url": "https://i.ytimg.com/vi/6OADNE5VKRM/mqdefault.jpg", "preference": -23, "id": "14"}, {"url": "https://i.ytimg.com/vi_webp/6OADNE5VKRM/mqdefault.webp", "height": 180, "width": 320, "preference": -22, "id": "15", "resolution": "320x180"}, {"url": "https://i.ytimg.com/vi/6OADNE5VKRM/0.jpg", "preference": -21, "id": "16"}, {"url": "https://i.ytimg.com/vi_webp/6OADNE5VKRM/0.webp", "preference": -20, "id": "17"}, {"url": "https://i.ytimg.com/vi/6OADNE5VKRM/hq3.jpg", "preference": -19, "id": "18"}, {"url": "https://i.ytimg.com/vi_webp/6OADNE5VKRM/hq3.webp", "preference": -18, "id": "19"}, {"url": "https://i.ytimg.com/vi/6OADNE5VKRM/hq2.jpg", "preference": -17, "id": "20"}, {"url": "https://i.ytimg.com/vi_webp/6OADNE5VKRM/hq2.webp", "preference": -16, "id": "21"}, {"url": "https://i.ytimg.com/vi/6OADNE5VKRM/hq1.jpg", "preference": -15, "id": "22"}, {"url": "https://i.ytimg.com/vi_webp/6OADNE5VKRM/hq1.webp", "preference": -14, "id": "23"}, {"url": "https://i.ytimg.com/vi/6OADNE5VKRM/hqdefault.jpg?sqp=-oaymwEbCKgBEF5IVfKriqkDDggBFQAAiEIYAXABwAEG&rs=AOn4CLDzgw_7cIHDiq9R5gDAxPliKXh8pg", "height": 94, "width": 168, "preference": -13, "id": "24", "resolution": "168x94"}, {"url": "https://i.ytimg.com/vi/6OADNE5VKRM/hqdefault.jpg?sqp=-oaymwEbCMQBEG5IVfKriqkDDggBFQAAiEIYAXABwAEG&rs=AOn4CLBaCrAuYwtK4lOTwj3YJY1jH9DUig", "height": 110, "width": 196, "preference": -13, "id": "25", "resolution": "196x110"}, {"url": "https://i.ytimg.com/vi/6OADNE5VKRM/hqdefault.jpg?sqp=-oaymwEcCPYBEIoBSFXyq4qpAw4IARUAAIhCGAFwAcABBg==&rs=AOn4CLCkyhMsTSSYBw5i51pLDBJUVDVITQ", "height": 138, "width": 246, "preference": -13, "id": "26", "resolution": "246x138"}, {"url": "https://i.ytimg.com/vi/6OADNE5VKRM/hqdefault.jpg?sqp=-oaymwEcCNACELwBSFXyq4qpAw4IARUAAIhCGAFwAcABBg==&rs=AOn4CLB1xvGicFKDLToqIwDh7zXGRyhWiQ", "height": 188, "width": 336, "preference": -13, "id": "27", "resolution": "336x188"}, {"url": "https://i.ytimg.com/vi/6OADNE5VKRM/hqdefault.jpg", "height": 360, "width": 480, "preference": -13, "id": "28", "resolution": "480x360"}, {"url": "https://i.ytimg.com/vi_webp/6OADNE5VKRM/hqdefault.webp", "height": 360, "width": 480, "preference": -12, "id": "29", "resolution": "480x360"}, {"url": "https://i.ytimg.com/vi/6OADNE5VKRM/sd3.jpg", "preference": -11, "id": "30"}, {"url": "https://i.ytimg.com/vi_webp/6OADNE5VKRM/sd3.webp", "preference": -10, "id": "31"}, {"url": "https://i.ytimg.com/vi/6OADNE5VKRM/sd2.jpg", "preference": -9, "id": "32"}, {"url": "https://i.ytimg.com/vi_webp/6OADNE5VKRM/sd2.webp", "preference": -8, "id": "33"}, {"url": "https://i.ytimg.com/vi/6OADNE5VKRM/sd1.jpg", "preference": -7, "id": "34"}, {"url": "https://i.ytimg.com/vi_webp/6OADNE5VKRM/sd1.webp", "preference": -6, "id": "35"}, {"url": "https://i.ytimg.com/vi/6OADNE5VKRM/sddefault.jpg", "preference": -5, "id": "36"}, {"url": "https://i.ytimg.com/vi_webp/6OADNE5VKRM/sddefault.webp", "height": 480, "width": 640, "preference": -4, "id": "37", "resolution": "640x480"}], "description": "This tutorial teaches you how to build my 360 cannon. I show how to add a simple variable timer using repeaters and also complex variable timer based on etherimp's original variable timer.\n\n(Related Videos)\nOriginal 360 Cannon: http://www.youtube.com/watch?v=-S3QH6hRRgg\nUnderwater 360 Cannon: http://www.youtube.com/watch?v=dW2uzPrKHl8\nNether 360 Cannon: http://www.youtube.com/watch?v=VP58Oqh0yRY\nVariable Timer Tutorial: http://www.youtube.com/watch?v=YZE784N-nQc", "upload_date": "20110624", "uploader": "EthosLab", "uploader_id": "EthosLab", "uploader_url": "http://www.youtube.com/user/EthosLab", "channel_id": "UCFKDEp9si4RmHFWJW1vYsMA", "channel_url": "https://www.youtube.com/channel/UCFKDEp9si4RmHFWJW1vYsMA", "duration": 2867, "view_count": 320665, "age_limit": 0, "webpage_url": "https://www.youtube.com/watch?v=6OADNE5VKRM", "categories": ["Gaming"], "tags": ["minecraft", "mine", "craft", "game", "etho", "let's", "lets", "play", "tutorial", "instruction", "creeper", "zombie", "skeleton", "world", "boat", "cart", "station", "survival", "dispenser", "beta", "epic", "mob", "trap", "grinder", "eats", "redstone", "red", "stone", "circuit", "water", "lava", "elevator", "fire", "track", "house", "base", "mining", "digging", "diamond", "invention", "mechanism", "fun", "notch", "cave", "360", "cannon"], "playable_in_embed": true, "is_live": false, "was_live": false, "live_status": "not_live", "like_count": 2281, "channel": "EthosLab", "availability": "public", "webpage_url_basename": "watch", "extractor": "youtube", "extractor_key": "Youtube", "n_entries": 50, "playlist_index": 26, "playlist": "Minecraft - Tutorial", "playlist_id": "PLaOY2J77tsfuEqgjKWxFxXWqZTViRjUxW", "playlist_title": "Minecraft - Tutorial", "playlist_uploader": "Playlists", "playlist_uploader_id": "UC8myOLsYDH1vqYtjFhimrqQ", "thumbnail": "https://i.ytimg.com/vi_webp/6OADNE5VKRM/sddefault.webp", "display_id": "6OADNE5VKRM", "asr": 44100, "filesize": 235895564, "format_id": "18", "format_note": "360p", "fps": 30, "height": 360, "quality": 6, "tbr": 658.137, "url": "https://rr2---sn-ab5sznld.googlevideo.com/videoplayback?expire=1641451455&ei=XzvWYYG9L72P2LYPtuuV0Aw&ip=68.70.26.44&id=o-AG-JD-cUGc6gTEYW_rNJ684PpL-oj-PJNnz6y2nk317U&itag=18&source=youtube&requiressl=yes&mh=QR&mm=31%2C26&mn=sn-ab5sznld%2Csn-p5qlsnrl&ms=au%2Conr&mv=m&mvi=2&pl=20&initcwndbps=2248750&vprv=1&mime=video%2Fmp4&gir=yes&clen=235895564&ratebypass=yes&dur=2867.432&lmt=1568852551743823&mt=1641429661&fvip=2&fexp=24001373%2C24007246&c=ANDROID&txp=1311222&sparams=expire%2Cei%2Cip%2Cid%2Citag%2Csource%2Crequiressl%2Cvprv%2Cmime%2Cgir%2Cclen%2Cratebypass%2Cdur%2Clmt&sig=AOq0QJ8wRgIhANv-NBGZEcxoK1gfg20ed7ZCQOMWrmpnjTYmwhN9uKTxAiEAzMTwrKoOx8Y2veM4D5ZPChXtsAAkkq86BHwBoc-y3sU%3D&lsparams=mh%2Cmm%2Cmn%2Cms%2Cmv%2Cmvi%2Cpl%2Cinitcwndbps&lsig=AG3C_xAwRQIgdSr9lkU7lcCXcnHfMsxexE6cJpGI8p0MhYIlWG4ziE0CIQCE7Ol6mDk0-l2bFpfX36I5Iqd5h5GF5FBntUr0EmoznQ%3D%3D", "width": 640, "language": "", "language_preference": -1, "ext": "mp4", "vcodec": "avc1.42001E", "acodec": "mp4a.40.2", "protocol": "https", "video_ext": "mp4", "audio_ext": "none", "vbr": 658.137, "abr": 0.0, "format": "18 - 640x360 (360p)", "http_headers": {"User-Agent": "Mozilla/5.0 (Windows NT 10.0; Win64; x64) AppleWebKit/537.36 (KHTML, like Gecko) Chrome/74.0.3718.8 Safari/537.36", "Accept-Charset": "ISO-8859-1,utf-8;q=0.7,*;q=0.7", "Accept": "text/html,application/xhtml+xml,application/xml;q=0.9,*/*;q=0.8", "Accept-Encoding": "gzip, deflate", "Accept-Language": "en-us,en;q=0.5"}, "fulltitle": "Minecraft - Tutorial: 360 Cannon", "epoch": 1641429859}