{"id": "k2rCn74gnAs", "title": "ARK Survival Evolved PVP #4: Flight For All", "formats": [{"asr": 22050, "filesize": 10561451, "format_id": "139", "format_note": "low", "quality": 2, "tbr": 47.579, "url": "https://rr1---sn-ab5sznle.googlevideo.com/videoplayback?expire=1641438830&ei=DgrWYYHwB4_08gTsyoGQCw&ip=68.70.26.44&id=o-AKihYnUGZNK-nm3zs0lt1HySprvzOQ4sdtJqX4G59nVj&itag=139&source=youtube&requiressl=yes&mh=xl&mm=31%2C29&mn=sn-ab5sznle%2Csn-ab5l6ndy&ms=au%2Crdu&mv=m&mvi=1&pl=20&initcwndbps=1412500&vprv=1&mime=audio%2Fmp4&gir=yes&clen=10561451&dur=1775.815&lmt=1457695064409702&mt=1641416931&fvip=1&keepalive=yes&fexp=24001373%2C24007246&c=ANDROID&sparams=expire%2Cei%2Cip%2Cid%2Citag%2Csource%2Crequiressl%2Cvprv%2Cmime%2Cgir%2Cclen%2Cdur%2Clmt&sig=AOq0QJ8wRgIhAIJ_UhQ8oPIbNVN-AZwkLJ15hAgb-dg_eF3qbW-2Zu--AiEA8ObjBJkCQrAu0oJy6VumHkHygbkXUe4QCC3ZXu082XI%3D&lsparams=mh%2Cmm%2Cmn%2Cms%2Cmv%2Cmvi%2Cpl%2Cinitcwndbps&lsig=AG3C_xAwRQIhAOYXo-_JVdAk1vvtiXEwRyRvbt1SvR7lGKXBJa-zhdMWAiASE0jgowU1hWlQ9BmgNeSAfBZFvS7Rz7mflCGSo9sZrw%3D%3D", "language": "", "language_preference": -1, "ext": "m4a", "vcodec": "none", "acodec": "mp4a.40.5", "abr": 47.579, "downloader_options": {"http_chunk_size": 10485760}, "container": "m4a_dash", "protocol": "https", "audio_ext": "m4a", "video_ext": "none", "format": "139 - audio only (low)", "http_headers": {"User-Agent": "Mozilla/5.0 (Windows NT 10.0; Win64; x64) AppleWebKit/537.36 (KHTML, like Gecko) Chrome/71.0.3569.1 Safari/537.36", "Accept-Charset": "ISO-8859-1,utf-8;q=0.7,*;q=0.7", "Accept": "text/html,application/xhtml+xml,application/xml;q=0.9,*/*;q=0.8", "Accept-Encoding": "gzip, deflate", "Accept-Language": "en-us,en;q=0.5"}}, {"asr": 48000, "filesize": 11276152, "format_id": "249", "format_note": "low", "quality": 2, "tbr": 50.802, "url": "https://rr1---sn-ab5sznle.googlevideo.com/videoplayback?expire=1641438830&ei=DgrWYYHwB4_08gTsyoGQCw&ip=68.70.26.44&id=o-AKihYnUGZNK-nm3zs0lt1HySprvzOQ4sdtJqX4G59nVj&itag=249&source=youtube&requiressl=yes&mh=xl&mm=31%2C29&mn=sn-ab5sznle%2Csn-ab5l6ndy&ms=au%2Crdu&mv=m&mvi=1&pl=20&initcwndbps=1412500&vprv=1&mime=audio%2Fwebm&gir=yes&clen=11276152&dur=1775.681&lmt=1457580482941952&mt=1641416931&fvip=1&keepalive=yes&fexp=24001373%2C24007246&c=ANDROID&sparams=expire%2Cei%2Cip%2Cid%2Citag%2Csource%2Crequiressl%2Cvprv%2Cmime%2Cgir%2Cclen%2Cdur%2Clmt&sig=AOq0QJ8wRAIgfvSsyv-_rsC-SNbamZw1qLsx11LCbjC3_Zf9w6YX6BsCIB--QnmhjmPp0Wg2mv_QzOEBbnGq-SYkxBWRC3WH1CKx&lsparams=mh%2Cmm%2Cmn%2Cms%2Cmv%2Cmvi%2Cpl%2Cinitcwndbps&lsig=AG3C_xAwRQIhAOYXo-_JVdAk1vvtiXEwRyRvbt1SvR7lGKXBJa-zhdMWAiASE0jgowU1hWlQ9BmgNeSAfBZFvS7Rz7mflCGSo9sZrw%3D%3D", "language": "", "language_preference": -1, "ext": "webm", "vcodec": "none", "acodec": "opus", "abr": 50.802, "downloader_options": {"http_chunk_size": 10485760}, "container": "webm_dash", "protocol": "https", "audio_ext": "webm", "video_ext": "none", "format": "249 - audio only (low)", "http_headers": {"User-Agent": "Mozilla/5.0 (Windows NT 10.0; Win64; x64) AppleWebKit/537.36 (KHTML, like Gecko) Chrome/71.0.3569.1 Safari/537.36", "Accept-Charset": "ISO-8859-1,utf-8;q=0.7,*;q=0.7", "Accept": "text/html,application/xhtml+xml,application/xml;q=0.9,*/*;q=0.8", "Accept-Encoding": "gzip, deflate", "Accept-Language": "en-us,en;q=0.5"}}, {"asr": 48000, "filesize": 14301644, "format_id": "250", "format_note": "low", "quality": 2, "tbr": 64.433, "url": "https://rr1---sn-ab5sznle.googlevideo.com/videoplayback?expire=1641438830&ei=DgrWYYHwB4_08gTsyoGQCw&ip=68.70.26.44&id=o-AKihYnUGZNK-nm3zs0lt1HySprvzOQ4sdtJqX4G59nVj&itag=250&source=youtube&requiressl=yes&mh=xl&mm=31%2C29&mn=sn-ab5sznle%2Csn-ab5l6ndy&ms=au%2Crdu&mv=m&mvi=1&pl=20&initcwndbps=1412500&vprv=1&mime=audio%2Fwebm&gir=yes&clen=14301644&dur=1775.681&lmt=1457580486971593&mt=1641416931&fvip=1&keepalive=yes&fexp=24001373%2C24007246&c=ANDROID&sparams=expire%2Cei%2Cip%2Cid%2Citag%2Csource%2Crequiressl%2Cvprv%2Cmime%2Cgir%2Cclen%2Cdur%2Clmt&sig=AOq0QJ8wRQIhANRuT7YoWC3FDdq_q2MgEcWzJIt3F596xlf4jvHtWfiTAiBMwTwHcJDMtToLKBpYt4ESBhCPfSOMp5YTlzFWZKFY7A%3D%3D&lsparams=mh%2Cmm%2Cmn%2Cms%2Cmv%2Cmvi%2Cpl%2Cinitcwndbps&lsig=AG3C_xAwRQIhAOYXo-_JVdAk1vvtiXEwRyRvbt1SvR7lGKXBJa-zhdMWAiASE0jgowU1hWlQ9BmgNeSAfBZFvS7Rz7mflCGSo9sZrw%3D%3D", "language": "", "language_preference": -1, "ext": "webm", "vcodec": "none", "acodec": "opus", "abr": 64.433, "downloader_options": {"http_chunk_size": 10485760}, "container": "webm_dash", "protocol": "https", "audio_ext": "webm", "video_ext": "none", "format": "250 - audio only (low)", "http_headers": {"User-Agent": "Mozilla/5.0 (Windows NT 10.0; Win64; x64) AppleWebKit/537.36 (KHTML, like Gecko) Chrome/71.0.3569.1 Safari/537.36", "Accept-Charset": "ISO-8859-1,utf-8;q=0.7,*;q=0.7", "Accept": "text/html,application/xhtml+xml,application/xml;q=0.9,*/*;q=0.8", "Accept-Encoding": "gzip, deflate", "Accept-Language": "en-us,en;q=0.5"}}, {"asr": 44100, "filesize": 28203414, "format_id": "140", "format_note": "medium", "quality": 3, "tbr": 127.062, "url": "https://rr1---sn-ab5sznle.googlevideo.com/videoplayback?expire=1641438830&ei=DgrWYYHwB4_08gTsyoGQCw&ip=68.70.26.44&id=o-AKihYnUGZNK-nm3zs0lt1HySprvzOQ4sdtJqX4G59nVj&itag=140&source=youtube&requiressl=yes&mh=xl&mm=31%2C29&mn=sn-ab5sznle%2Csn-ab5l6ndy&ms=au%2Crdu&mv=m&mvi=1&pl=20&initcwndbps=1412500&vprv=1&mime=audio%2Fmp4&gir=yes&clen=28203414&dur=1775.722&lmt=1457695064561284&mt=1641416931&fvip=1&keepalive=yes&fexp=24001373%2C24007246&c=ANDROID&sparams=expire%2Cei%2Cip%2Cid%2Citag%2Csource%2Crequiressl%2Cvprv%2Cmime%2Cgir%2Cclen%2Cdur%2Clmt&sig=AOq0QJ8wRQIhAPlUDzum4QRMgLjogSYWhOwT9vMD8vB4Hy1HOY3QN_HrAiBDmEVvjvQtLRB0Ln5uezYwM0IV16YHEia--JVGkBhSpQ%3D%3D&lsparams=mh%2Cmm%2Cmn%2Cms%2Cmv%2Cmvi%2Cpl%2Cinitcwndbps&lsig=AG3C_xAwRQIhAOYXo-_JVdAk1vvtiXEwRyRvbt1SvR7lGKXBJa-zhdMWAiASE0jgowU1hWlQ9BmgNeSAfBZFvS7Rz7mflCGSo9sZrw%3D%3D", "language": "", "language_preference": -1, "ext": "m4a", "vcodec": "none", "acodec": "mp4a.40.2", "abr": 127.062, "downloader_options": {"http_chunk_size": 10485760}, "container": "m4a_dash", "protocol": "https", "audio_ext": "m4a", "video_ext": "none", "format": "140 - audio only (medium)", "http_headers": {"User-Agent": "Mozilla/5.0 (Windows NT 10.0; Win64; x64) AppleWebKit/537.36 (KHTML, like Gecko) Chrome/71.0.3569.1 Safari/537.36", "Accept-Charset": "ISO-8859-1,utf-8;q=0.7,*;q=0.7", "Accept": "text/html,application/xhtml+xml,application/xml;q=0.9,*/*;q=0.8", "Accept-Encoding": "gzip, deflate", "Accept-Language": "en-us,en;q=0.5"}}, {"asr": 48000, "filesize": 26974464, "format_id": "251", "format_note": "medium", "quality": 3, "tbr": 121.528, "url": "https://rr1---sn-ab5sznle.googlevideo.com/videoplayback?expire=1641438830&ei=DgrWYYHwB4_08gTsyoGQCw&ip=68.70.26.44&id=o-AKihYnUGZNK-nm3zs0lt1HySprvzOQ4sdtJqX4G59nVj&itag=251&source=youtube&requiressl=yes&mh=xl&mm=31%2C29&mn=sn-ab5sznle%2Csn-ab5l6ndy&ms=au%2Crdu&mv=m&mvi=1&pl=20&initcwndbps=1412500&vprv=1&mime=audio%2Fwebm&gir=yes&clen=26974464&dur=1775.681&lmt=1457580485358910&mt=1641416931&fvip=1&keepalive=yes&fexp=24001373%2C24007246&c=ANDROID&sparams=expire%2Cei%2Cip%2Cid%2Citag%2Csource%2Crequiressl%2Cvprv%2Cmime%2Cgir%2Cclen%2Cdur%2Clmt&sig=AOq0QJ8wRQIgWqpppIH7ZUJVc9XDSauxWT0VaODHj1EdfY8HcYwZ-XECIQDrInKCWish7L117MkwG6iaAVUNXxt7G4ZOPmAu0yl6gw%3D%3D&lsparams=mh%2Cmm%2Cmn%2Cms%2Cmv%2Cmvi%2Cpl%2Cinitcwndbps&lsig=AG3C_xAwRQIhAOYXo-_JVdAk1vvtiXEwRyRvbt1SvR7lGKXBJa-zhdMWAiASE0jgowU1hWlQ9BmgNeSAfBZFvS7Rz7mflCGSo9sZrw%3D%3D", "language": "", "language_preference": -1, "ext": "webm", "vcodec": "none", "acodec": "opus", "abr": 121.528, "downloader_options": {"http_chunk_size": 10485760}, "container": "webm_dash", "protocol": "https", "audio_ext": "webm", "video_ext": "none", "format": "251 - audio only (medium)", "http_headers": {"User-Agent": "Mozilla/5.0 (Windows NT 10.0; Win64; x64) AppleWebKit/537.36 (KHTML, like Gecko) Chrome/71.0.3569.1 Safari/537.36", "Accept-Charset": "ISO-8859-1,utf-8;q=0.7,*;q=0.7", "Accept": "text/html,application/xhtml+xml,application/xml;q=0.9,*/*;q=0.8", "Accept-Encoding": "gzip, deflate", "Accept-Language": "en-us,en;q=0.5"}}, {"asr": 22050, "filesize": 17553631, "format_id": "17", "format_note": "144p", "fps": 10, "height": 144, "quality": 0, "tbr": 79.08, "url": "https://rr1---sn-ab5sznle.googlevideo.com/videoplayback?expire=1641438830&ei=DgrWYYHwB4_08gTsyoGQCw&ip=68.70.26.44&id=o-AKihYnUGZNK-nm3zs0lt1HySprvzOQ4sdtJqX4G59nVj&itag=17&source=youtube&requiressl=yes&mh=xl&mm=31%2C29&mn=sn-ab5sznle%2Csn-ab5l6ndy&ms=au%2Crdu&mv=m&mvi=1&pl=20&initcwndbps=1412500&vprv=1&mime=video%2F3gpp&gir=yes&clen=17553631&dur=1775.769&lmt=1457578751374611&mt=1641416931&fvip=1&fexp=24001373%2C24007246&c=ANDROID&sparams=expire%2Cei%2Cip%2Cid%2Citag%2Csource%2Crequiressl%2Cvprv%2Cmime%2Cgir%2Cclen%2Cdur%2Clmt&sig=AOq0QJ8wRQIgSYsOhzfdocsdE2GMlqbo23bKVmWg4Z5lVxbR4d-hXugCIQDmwgf06qS754fwG1DsR0TqMHTrRQdISqOY6Z0HQECMBQ%3D%3D&lsparams=mh%2Cmm%2Cmn%2Cms%2Cmv%2Cmvi%2Cpl%2Cinitcwndbps&lsig=AG3C_xAwRQIhAOYXo-_JVdAk1vvtiXEwRyRvbt1SvR7lGKXBJa-zhdMWAiASE0jgowU1hWlQ9BmgNeSAfBZFvS7Rz7mflCGSo9sZrw%3D%3D", "width": 176, "language": "", "language_preference": -1, "ext": "3gp", "vcodec": "mp4v.20.3", "acodec": "mp4a.40.2", "protocol": "https", "video_ext": "3gp", "audio_ext": "none", "vbr": 79.08, "abr": 0.0, "format": "17 - 176x144 (144p)", "http_headers": {"User-Agent": "Mozilla/5.0 (Windows NT 10.0; Win64; x64) AppleWebKit/537.36 (KHTML, like Gecko) Chrome/71.0.3569.1 Safari/537.36", "Accept-Charset": "ISO-8859-1,utf-8;q=0.7,*;q=0.7", "Accept": "text/html,application/xhtml+xml,application/xml;q=0.9,*/*;q=0.8", "Accept-Encoding": "gzip, deflate", "Accept-Language": "en-us,en;q=0.5"}}, {"filesize": 24419948, "format_id": "160", "format_note": "144p", "fps": 30, "height": 144, "quality": 0, "tbr": 110.02, "url": "https://rr1---sn-ab5sznle.googlevideo.com/videoplayback?expire=1641438830&ei=DgrWYYHwB4_08gTsyoGQCw&ip=68.70.26.44&id=o-AKihYnUGZNK-nm3zs0lt1HySprvzOQ4sdtJqX4G59nVj&itag=160&source=youtube&requiressl=yes&mh=xl&mm=31%2C29&mn=sn-ab5sznle%2Csn-ab5l6ndy&ms=au%2Crdu&mv=m&mvi=1&pl=20&initcwndbps=1412500&vprv=1&mime=video%2Fmp4&gir=yes&clen=24419948&dur=1775.666&lmt=1457698064686247&mt=1641416931&fvip=1&keepalive=yes&fexp=24001373%2C24007246&c=ANDROID&sparams=expire%2Cei%2Cip%2Cid%2Citag%2Csource%2Crequiressl%2Cvprv%2Cmime%2Cgir%2Cclen%2Cdur%2Clmt&sig=AOq0QJ8wRQIgGdfyK6SQSVQOEHIlLW5YdkNEkC8R0N9prBmO7AxQhPgCIQCW4Rs17aFkE4IDcNMDJ_Xz9d1V97yJMRtCduXtOLyvZQ%3D%3D&lsparams=mh%2Cmm%2Cmn%2Cms%2Cmv%2Cmvi%2Cpl%2Cinitcwndbps&lsig=AG3C_xAwRQIhAOYXo-_JVdAk1vvtiXEwRyRvbt1SvR7lGKXBJa-zhdMWAiASE0jgowU1hWlQ9BmgNeSAfBZFvS7Rz7mflCGSo9sZrw%3D%3D", "width": 256, "language": "", "language_preference": -1, "ext": "mp4", "vcodec": "avc1.4d400c", "acodec": "none", "vbr": 110.02, "downloader_options": {"http_chunk_size": 10485760}, "container": "mp4_dash", "protocol": "https", "video_ext": "mp4", "audio_ext": "none", "format": "160 - 256x144 (144p)", "http_headers": {"User-Agent": "Mozilla/5.0 (Windows NT 10.0; Win64; x64) AppleWebKit/537.36 (KHTML, like Gecko) Chrome/71.0.3569.1 Safari/537.36", "Accept-Charset": "ISO-8859-1,utf-8;q=0.7,*;q=0.7", "Accept": "text/html,application/xhtml+xml,application/xml;q=0.9,*/*;q=0.8", "Accept-Encoding": "gzip, deflate", "Accept-Language": "en-us,en;q=0.5"}}, {"filesize": 22762352, "format_id": "278", "format_note": "144p", "fps": 30, "height": 144, "quality": 0, "tbr": 102.554, "url": "https://rr1---sn-ab5sznle.googlevideo.com/videoplayback?expire=1641438830&ei=DgrWYYHwB4_08gTsyoGQCw&ip=68.70.26.44&id=o-AKihYnUGZNK-nm3zs0lt1HySprvzOQ4sdtJqX4G59nVj&itag=278&source=youtube&requiressl=yes&mh=xl&mm=31%2C29&mn=sn-ab5sznle%2Csn-ab5l6ndy&ms=au%2Crdu&mv=m&mvi=1&pl=20&initcwndbps=1412500&vprv=1&mime=video%2Fwebm&gir=yes&clen=22762352&dur=1775.633&lmt=1457587478803508&mt=1641416931&fvip=1&keepalive=yes&fexp=24001373%2C24007246&c=ANDROID&sparams=expire%2Cei%2Cip%2Cid%2Citag%2Csource%2Crequiressl%2Cvprv%2Cmime%2Cgir%2Cclen%2Cdur%2Clmt&sig=AOq0QJ8wRgIhAKQ-3UkgloNjjAIwJu2RULC6g8bJ6uOSy3p95iu8NctWAiEAh4n3B3Tj7Z7pOsOXqYbaTWHF1KHVbhnpY6RnB9yNezQ%3D&lsparams=mh%2Cmm%2Cmn%2Cms%2Cmv%2Cmvi%2Cpl%2Cinitcwndbps&lsig=AG3C_xAwRQIhAOYXo-_JVdAk1vvtiXEwRyRvbt1SvR7lGKXBJa-zhdMWAiASE0jgowU1hWlQ9BmgNeSAfBZFvS7Rz7mflCGSo9sZrw%3D%3D", "width": 256, "language": "", "language_preference": -1, "ext": "webm", "vcodec": "vp9", "acodec": "none", "vbr": 102.554, "downloader_options": {"http_chunk_size": 10485760}, "container": "webm_dash", "protocol": "https", "video_ext": "webm", "audio_ext": "none", "format": "278 - 256x144 (144p)", "http_headers": {"User-Agent": "Mozilla/5.0 (Windows NT 10.0; Win64; x64) AppleWebKit/537.36 (KHTML, like Gecko) Chrome/71.0.3569.1 Safari/537.36", "Accept-Charset": "ISO-8859-1,utf-8;q=0.7,*;q=0.7", "Accept": "text/html,application/xhtml+xml,application/xml;q=0.9,*/*;q=0.8", "Accept-Encoding": "gzip, deflate", "Accept-Language": "en-us,en;q=0.5"}}, {"filesize": 54724653, "format_id": "133", "format_note": "240p", "fps": 30, "height": 240, "quality": 5, "tbr": 246.553, "url": "https://rr1---sn-ab5sznle.googlevideo.com/videoplayback?expire=1641438830&ei=DgrWYYHwB4_08gTsyoGQCw&ip=68.70.26.44&id=o-AKihYnUGZNK-nm3zs0lt1HySprvzOQ4sdtJqX4G59nVj&itag=133&source=youtube&requiressl=yes&mh=xl&mm=31%2C29&mn=sn-ab5sznle%2Csn-ab5l6ndy&ms=au%2Crdu&mv=m&mvi=1&pl=20&initcwndbps=1412500&vprv=1&mime=video%2Fmp4&gir=yes&clen=54724653&dur=1775.666&lmt=1457698070652368&mt=1641416931&fvip=1&keepalive=yes&fexp=24001373%2C24007246&c=ANDROID&sparams=expire%2Cei%2Cip%2Cid%2Citag%2Csource%2Crequiressl%2Cvprv%2Cmime%2Cgir%2Cclen%2Cdur%2Clmt&sig=AOq0QJ8wRQIhANSjYcamj1twn54GUstcBQdChq4PWhUcsOXzLhdni9baAiA8ygHtwvAUMONZkGosxGaZZP_gvfc-CYowQeMpBep1tA%3D%3D&lsparams=mh%2Cmm%2Cmn%2Cms%2Cmv%2Cmvi%2Cpl%2Cinitcwndbps&lsig=AG3C_xAwRQIhAOYXo-_JVdAk1vvtiXEwRyRvbt1SvR7lGKXBJa-zhdMWAiASE0jgowU1hWlQ9BmgNeSAfBZFvS7Rz7mflCGSo9sZrw%3D%3D", "width": 426, "language": "", "language_preference": -1, "ext": "mp4", "vcodec": "avc1.4d4015", "acodec": "none", "vbr": 246.553, "downloader_options": {"http_chunk_size": 10485760}, "container": "mp4_dash", "protocol": "https", "video_ext": "mp4", "audio_ext": "none", "format": "133 - 426x240 (240p)", "http_headers": {"User-Agent": "Mozilla/5.0 (Windows NT 10.0; Win64; x64) AppleWebKit/537.36 (KHTML, like Gecko) Chrome/71.0.3569.1 Safari/537.36", "Accept-Charset": "ISO-8859-1,utf-8;q=0.7,*;q=0.7", "Accept": "text/html,application/xhtml+xml,application/xml;q=0.9,*/*;q=0.8", "Accept-Encoding": "gzip, deflate", "Accept-Language": "en-us,en;q=0.5"}}, {"filesize": 49556750, "format_id": "242", "format_note": "240p", "fps": 30, "height": 240, "quality": 5, "tbr": 223.274, "url": "https://rr1---sn-ab5sznle.googlevideo.com/videoplayback?expire=1641438830&ei=DgrWYYHwB4_08gTsyoGQCw&ip=68.70.26.44&id=o-AKihYnUGZNK-nm3zs0lt1HySprvzOQ4sdtJqX4G59nVj&itag=242&source=youtube&requiressl=yes&mh=xl&mm=31%2C29&mn=sn-ab5sznle%2Csn-ab5l6ndy&ms=au%2Crdu&mv=m&mvi=1&pl=20&initcwndbps=1412500&vprv=1&mime=video%2Fwebm&gir=yes&clen=49556750&dur=1775.633&lmt=1457587481353350&mt=1641416931&fvip=1&keepalive=yes&fexp=24001373%2C24007246&c=ANDROID&sparams=expire%2Cei%2Cip%2Cid%2Citag%2Csource%2Crequiressl%2Cvprv%2Cmime%2Cgir%2Cclen%2Cdur%2Clmt&sig=AOq0QJ8wRgIhAKhhmsXGwrGgBGNR-qG1JkYJaQLIFBnLqrpSEk3jm4ikAiEAt8AJ6SXYBVtPWhrfEF07vEiXkJtKzKc-hYD9H_LF_kg%3D&lsparams=mh%2Cmm%2Cmn%2Cms%2Cmv%2Cmvi%2Cpl%2Cinitcwndbps&lsig=AG3C_xAwRQIhAOYXo-_JVdAk1vvtiXEwRyRvbt1SvR7lGKXBJa-zhdMWAiASE0jgowU1hWlQ9BmgNeSAfBZFvS7Rz7mflCGSo9sZrw%3D%3D", "width": 426, "language": "", "language_preference": -1, "ext": "webm", "vcodec": "vp9", "acodec": "none", "vbr": 223.274, "downloader_options": {"http_chunk_size": 10485760}, "container": "webm_dash", "protocol": "https", "video_ext": "webm", "audio_ext": "none", "format": "242 - 426x240 (240p)", "http_headers": {"User-Agent": "Mozilla/5.0 (Windows NT 10.0; Win64; x64) AppleWebKit/537.36 (KHTML, like Gecko) Chrome/71.0.3569.1 Safari/537.36", "Accept-Charset": "ISO-8859-1,utf-8;q=0.7,*;q=0.7", "Accept": "text/html,application/xhtml+xml,application/xml;q=0.9,*/*;q=0.8", "Accept-Encoding": "gzip, deflate", "Accept-Language": "en-us,en;q=0.5"}}, {"filesize": 117859841, "format_id": "134", "format_note": "360p", "fps": 30, "height": 360, "quality": 6, "tbr": 531.0, "url": "https://rr1---sn-ab5sznle.googlevideo.com/videoplayback?expire=1641438830&ei=DgrWYYHwB4_08gTsyoGQCw&ip=68.70.26.44&id=o-AKihYnUGZNK-nm3zs0lt1HySprvzOQ4sdtJqX4G59nVj&itag=134&source=youtube&requiressl=yes&mh=xl&mm=31%2C29&mn=sn-ab5sznle%2Csn-ab5l6ndy&ms=au%2Crdu&mv=m&mvi=1&pl=20&initcwndbps=1412500&vprv=1&mime=video%2Fmp4&gir=yes&clen=117859841&dur=1775.666&lmt=1457698107086261&mt=1641416931&fvip=1&keepalive=yes&fexp=24001373%2C24007246&c=ANDROID&sparams=expire%2Cei%2Cip%2Cid%2Citag%2Csource%2Crequiressl%2Cvprv%2Cmime%2Cgir%2Cclen%2Cdur%2Clmt&sig=AOq0QJ8wRQIgMR0jk_eTSEONzQuNzZqrY_BHlg3xlSq8Q9ZMiTfmW_0CIQCeGNYeWEGtGAqa4FRxivF5Mh6pZOQe5EIRRkhNgTLLxg%3D%3D&lsparams=mh%2Cmm%2Cmn%2Cms%2Cmv%2Cmvi%2Cpl%2Cinitcwndbps&lsig=AG3C_xAwRQIhAOYXo-_JVdAk1vvtiXEwRyRvbt1SvR7lGKXBJa-zhdMWAiASE0jgowU1hWlQ9BmgNeSAfBZFvS7Rz7mflCGSo9sZrw%3D%3D", "width": 640, "language": "", "language_preference": -1, "ext": "mp4", "vcodec": "avc1.4d401e", "acodec": "none", "vbr": 531.0, "downloader_options": {"http_chunk_size": 10485760}, "container": "mp4_dash", "protocol": "https", "video_ext": "mp4", "audio_ext": "none", "format": "134 - 640x360 (360p)", "http_headers": {"User-Agent": "Mozilla/5.0 (Windows NT 10.0; Win64; x64) AppleWebKit/537.36 (KHTML, like Gecko) Chrome/71.0.3569.1 Safari/537.36", "Accept-Charset": "ISO-8859-1,utf-8;q=0.7,*;q=0.7", "Accept": "text/html,application/xhtml+xml,application/xml;q=0.9,*/*;q=0.8", "Accept-Encoding": "gzip, deflate", "Accept-Language": "en-us,en;q=0.5"}}, {"asr": 44100, "filesize": 161487411, "format_id": "18", "format_note": "360p", "fps": 30, "height": 360, "quality": 6, "tbr": 727.534, "url": "https://rr1---sn-ab5sznle.googlevideo.com/videoplayback?expire=1641438830&ei=DgrWYYHwB4_08gTsyoGQCw&ip=68.70.26.44&id=o-AKihYnUGZNK-nm3zs0lt1HySprvzOQ4sdtJqX4G59nVj&itag=18&source=youtube&requiressl=yes&mh=xl&mm=31%2C29&mn=sn-ab5sznle%2Csn-ab5l6ndy&ms=au%2Crdu&mv=m&mvi=1&pl=20&initcwndbps=1412500&vprv=1&mime=video%2Fmp4&gir=yes&clen=161487411&ratebypass=yes&dur=1775.722&lmt=1457695694996317&mt=1641416931&fvip=1&fexp=24001373%2C24007246&c=ANDROID&sparams=expire%2Cei%2Cip%2Cid%2Citag%2Csource%2Crequiressl%2Cvprv%2Cmime%2Cgir%2Cclen%2Cratebypass%2Cdur%2Clmt&sig=AOq0QJ8wRQIgJ_RWthzX35zSnzC_QEBqslil9TCMUpQswA1QDB8ZGnACIQD1QpXLXbC0BHDVonJ76AJMbckKhtGG-uF4WGUcz2oBKw%3D%3D&lsparams=mh%2Cmm%2Cmn%2Cms%2Cmv%2Cmvi%2Cpl%2Cinitcwndbps&lsig=AG3C_xAwRQIhAOYXo-_JVdAk1vvtiXEwRyRvbt1SvR7lGKXBJa-zhdMWAiASE0jgowU1hWlQ9BmgNeSAfBZFvS7Rz7mflCGSo9sZrw%3D%3D", "width": 640, "language": "", "language_preference": -1, "ext": "mp4", "vcodec": "avc1.42001E", "acodec": "mp4a.40.2", "protocol": "https", "video_ext": "mp4", "audio_ext": "none", "vbr": 727.534, "abr": 0.0, "format": "18 - 640x360 (360p)", "http_headers": {"User-Agent": "Mozilla/5.0 (Windows NT 10.0; Win64; x64) AppleWebKit/537.36 (KHTML, like Gecko) Chrome/71.0.3569.1 Safari/537.36", "Accept-Charset": "ISO-8859-1,utf-8;q=0.7,*;q=0.7", "Accept": "text/html,application/xhtml+xml,application/xml;q=0.9,*/*;q=0.8", "Accept-Encoding": "gzip, deflate", "Accept-Language": "en-us,en;q=0.5"}}, {"filesize": 93295036, "format_id": "243", "format_note": "360p", "fps": 30, "height": 360, "quality": 6, "tbr": 420.334, "url": "https://rr1---sn-ab5sznle.googlevideo.com/videoplayback?expire=1641438830&ei=DgrWYYHwB4_08gTsyoGQCw&ip=68.70.26.44&id=o-AKihYnUGZNK-nm3zs0lt1HySprvzOQ4sdtJqX4G59nVj&itag=243&source=youtube&requiressl=yes&mh=xl&mm=31%2C29&mn=sn-ab5sznle%2Csn-ab5l6ndy&ms=au%2Crdu&mv=m&mvi=1&pl=20&initcwndbps=1412500&vprv=1&mime=video%2Fwebm&gir=yes&clen=93295036&dur=1775.633&lmt=1457587485887892&mt=1641416931&fvip=1&keepalive=yes&fexp=24001373%2C24007246&c=ANDROID&sparams=expire%2Cei%2Cip%2Cid%2Citag%2Csource%2Crequiressl%2Cvprv%2Cmime%2Cgir%2Cclen%2Cdur%2Clmt&sig=AOq0QJ8wRQIgdo9WrIxFsWGxXBiQRpcS6Bkszv8Ycfp4iPZNuRNOWsgCIQD-BUb604C21PtLyzUAh6c8RqswmTq0H9h6_JMfwbBh1Q%3D%3D&lsparams=mh%2Cmm%2Cmn%2Cms%2Cmv%2Cmvi%2Cpl%2Cinitcwndbps&lsig=AG3C_xAwRQIhAOYXo-_JVdAk1vvtiXEwRyRvbt1SvR7lGKXBJa-zhdMWAiASE0jgowU1hWlQ9BmgNeSAfBZFvS7Rz7mflCGSo9sZrw%3D%3D", "width": 640, "language": "", "language_preference": -1, "ext": "webm", "vcodec": "vp9", "acodec": "none", "vbr": 420.334, "downloader_options": {"http_chunk_size": 10485760}, "container": "webm_dash", "protocol": "https", "video_ext": "webm", "audio_ext": "none", "format": "243 - 640x360 (360p)", "http_headers": {"User-Agent": "Mozilla/5.0 (Windows NT 10.0; Win64; x64) AppleWebKit/537.36 (KHTML, like Gecko) Chrome/71.0.3569.1 Safari/537.36", "Accept-Charset": "ISO-8859-1,utf-8;q=0.7,*;q=0.7", "Accept": "text/html,application/xhtml+xml,application/xml;q=0.9,*/*;q=0.8", "Accept-Encoding": "gzip, deflate", "Accept-Language": "en-us,en;q=0.5"}}, {"filesize": 221430348, "format_id": "135", "format_note": "480p", "fps": 30, "height": 480, "quality": 7, "tbr": 997.621, "url": "https://rr1---sn-ab5sznle.googlevideo.com/videoplayback?expire=1641438830&ei=DgrWYYHwB4_08gTsyoGQCw&ip=68.70.26.44&id=o-AKihYnUGZNK-nm3zs0lt1HySprvzOQ4sdtJqX4G59nVj&itag=135&source=youtube&requiressl=yes&mh=xl&mm=31%2C29&mn=sn-ab5sznle%2Csn-ab5l6ndy&ms=au%2Crdu&mv=m&mvi=1&pl=20&initcwndbps=1412500&vprv=1&mime=video%2Fmp4&gir=yes&clen=221430348&dur=1775.666&lmt=1457698125476075&mt=1641416931&fvip=1&keepalive=yes&fexp=24001373%2C24007246&c=ANDROID&sparams=expire%2Cei%2Cip%2Cid%2Citag%2Csource%2Crequiressl%2Cvprv%2Cmime%2Cgir%2Cclen%2Cdur%2Clmt&sig=AOq0QJ8wRQIhAPQrsgj2xpijcPJLlmWKtPz44LuEkCDzwlr57WtMKfLiAiAFtU5HSfjEWjswIfetQudv1dCI3vxc97y_29Vpm3N4GA%3D%3D&lsparams=mh%2Cmm%2Cmn%2Cms%2Cmv%2Cmvi%2Cpl%2Cinitcwndbps&lsig=AG3C_xAwRQIhAOYXo-_JVdAk1vvtiXEwRyRvbt1SvR7lGKXBJa-zhdMWAiASE0jgowU1hWlQ9BmgNeSAfBZFvS7Rz7mflCGSo9sZrw%3D%3D", "width": 854, "language": "", "language_preference": -1, "ext": "mp4", "vcodec": "avc1.4d401f", "acodec": "none", "vbr": 997.621, "downloader_options": {"http_chunk_size": 10485760}, "container": "mp4_dash", "protocol": "https", "video_ext": "mp4", "audio_ext": "none", "format": "135 - 854x480 (480p)", "http_headers": {"User-Agent": "Mozilla/5.0 (Windows NT 10.0; Win64; x64) AppleWebKit/537.36 (KHTML, like Gecko) Chrome/71.0.3569.1 Safari/537.36", "Accept-Charset": "ISO-8859-1,utf-8;q=0.7,*;q=0.7", "Accept": "text/html,application/xhtml+xml,application/xml;q=0.9,*/*;q=0.8", "Accept-Encoding": "gzip, deflate", "Accept-Language": "en-us,en;q=0.5"}}, {"filesize": 169620061, "format_id": "244", "format_note": "480p", "fps": 30, "height": 480, "quality": 7, "tbr": 764.212, "url": "https://rr1---sn-ab5sznle.googlevideo.com/videoplayback?expire=1641438830&ei=DgrWYYHwB4_08gTsyoGQCw&ip=68.70.26.44&id=o-AKihYnUGZNK-nm3zs0lt1HySprvzOQ4sdtJqX4G59nVj&itag=244&source=youtube&requiressl=yes&mh=xl&mm=31%2C29&mn=sn-ab5sznle%2Csn-ab5l6ndy&ms=au%2Crdu&mv=m&mvi=1&pl=20&initcwndbps=1412500&vprv=1&mime=video%2Fwebm&gir=yes&clen=169620061&dur=1775.633&lmt=1457587539822679&mt=1641416931&fvip=1&keepalive=yes&fexp=24001373%2C24007246&c=ANDROID&sparams=expire%2Cei%2Cip%2Cid%2Citag%2Csource%2Crequiressl%2Cvprv%2Cmime%2Cgir%2Cclen%2Cdur%2Clmt&sig=AOq0QJ8wRAIgU9esoIYjCQitralS7Bouhriqlebpf84Q1Ai33ugJ_-ACIEp1nhFXnUExyb2LUyl7aEPF-j-1PiqU0AK1G2k8wDJM&lsparams=mh%2Cmm%2Cmn%2Cms%2Cmv%2Cmvi%2Cpl%2Cinitcwndbps&lsig=AG3C_xAwRQIhAOYXo-_JVdAk1vvtiXEwRyRvbt1SvR7lGKXBJa-zhdMWAiASE0jgowU1hWlQ9BmgNeSAfBZFvS7Rz7mflCGSo9sZrw%3D%3D", "width": 854, "language": "", "language_preference": -1, "ext": "webm", "vcodec": "vp9", "acodec": "none", "vbr": 764.212, "downloader_options": {"http_chunk_size": 10485760}, "container": "webm_dash", "protocol": "https", "video_ext": "webm", "audio_ext": "none", "format": "244 - 854x480 (480p)", "http_headers": {"User-Agent": "Mozilla/5.0 (Windows NT 10.0; Win64; x64) AppleWebKit/537.36 (KHTML, like Gecko) Chrome/71.0.3569.1 Safari/537.36", "Accept-Charset": "ISO-8859-1,utf-8;q=0.7,*;q=0.7", "Accept": "text/html,application/xhtml+xml,application/xml;q=0.9,*/*;q=0.8", "Accept-Encoding": "gzip, deflate", "Accept-Language": "en-us,en;q=0.5"}}, {"filesize": 433404971, "format_id": "136", "format_note": "720p", "fps": 30, "height": 720, "quality": 8, "tbr": 1952.641, "url": "https://rr1---sn-ab5sznle.googlevideo.com/videoplayback?expire=1641438830&ei=DgrWYYHwB4_08gTsyoGQCw&ip=68.70.26.44&id=o-AKihYnUGZNK-nm3zs0lt1HySprvzOQ4sdtJqX4G59nVj&itag=136&source=youtube&requiressl=yes&mh=xl&mm=31%2C29&mn=sn-ab5sznle%2Csn-ab5l6ndy&ms=au%2Crdu&mv=m&mvi=1&pl=20&initcwndbps=1412500&vprv=1&mime=video%2Fmp4&gir=yes&clen=433404971&dur=1775.666&lmt=1457698173012111&mt=1641416931&fvip=1&keepalive=yes&fexp=24001373%2C24007246&c=ANDROID&sparams=expire%2Cei%2Cip%2Cid%2Citag%2Csource%2Crequiressl%2Cvprv%2Cmime%2Cgir%2Cclen%2Cdur%2Clmt&sig=AOq0QJ8wRQIgYAEQWdUdq7E7fas8w7x5E6s58Wfy_dBkkSWk21EEAnICIQDUANtKCzwGV4yECcLTXVwvtiaVmHGRFcmlitReIxL14A%3D%3D&lsparams=mh%2Cmm%2Cmn%2Cms%2Cmv%2Cmvi%2Cpl%2Cinitcwndbps&lsig=AG3C_xAwRQIhAOYXo-_JVdAk1vvtiXEwRyRvbt1SvR7lGKXBJa-zhdMWAiASE0jgowU1hWlQ9BmgNeSAfBZFvS7Rz7mflCGSo9sZrw%3D%3D", "width": 1280, "language": "", "language_preference": -1, "ext": "mp4", "vcodec": "avc1.4d401f", "acodec": "none", "vbr": 1952.641, "downloader_options": {"http_chunk_size": 10485760}, "container": "mp4_dash", "protocol": "https", "video_ext": "mp4", "audio_ext": "none", "format": "136 - 1280x720 (720p)", "http_headers": {"User-Agent": "Mozilla/5.0 (Windows NT 10.0; Win64; x64) AppleWebKit/537.36 (KHTML, like Gecko) Chrome/71.0.3569.1 Safari/537.36", "Accept-Charset": "ISO-8859-1,utf-8;q=0.7,*;q=0.7", "Accept": "text/html,application/xhtml+xml,application/xml;q=0.9,*/*;q=0.8", "Accept-Encoding": "gzip, deflate", "Accept-Language": "en-us,en;q=0.5"}}, {"asr": 44100, "format_id": "22", "format_note": "720p", "fps": 30, "height": 720, "quality": 8, "tbr": 2079.033, "url": "https://rr1---sn-ab5sznle.googlevideo.com/videoplayback?expire=1641438830&ei=DgrWYYHwB4_08gTsyoGQCw&ip=68.70.26.44&id=o-AKihYnUGZNK-nm3zs0lt1HySprvzOQ4sdtJqX4G59nVj&itag=22&source=youtube&requiressl=yes&mh=xl&mm=31%2C29&mn=sn-ab5sznle%2Csn-ab5l6ndy&ms=au%2Crdu&mv=m&mvi=1&pl=20&initcwndbps=1412500&vprv=1&mime=video%2Fmp4&cnr=14&ratebypass=yes&dur=1775.722&lmt=1472390431796707&mt=1641416931&fvip=1&fexp=24001373%2C24007246&c=ANDROID&sparams=expire%2Cei%2Cip%2Cid%2Citag%2Csource%2Crequiressl%2Cvprv%2Cmime%2Ccnr%2Cratebypass%2Cdur%2Clmt&sig=AOq0QJ8wRgIhAI9hPkFw3KqEjk0yQfC11zvtJ09vNN5dXKtSHppN-h-IAiEArKrspTswZUO0e0Kd30xi-jRm_3hktsJfWe8i7AQ3bhw%3D&lsparams=mh%2Cmm%2Cmn%2Cms%2Cmv%2Cmvi%2Cpl%2Cinitcwndbps&lsig=AG3C_xAwRQIhAOYXo-_JVdAk1vvtiXEwRyRvbt1SvR7lGKXBJa-zhdMWAiASE0jgowU1hWlQ9BmgNeSAfBZFvS7Rz7mflCGSo9sZrw%3D%3D", "width": 1280, "language": "", "language_preference": -1, "ext": "mp4", "vcodec": "avc1.64001F", "acodec": "mp4a.40.2", "protocol": "https", "video_ext": "mp4", "audio_ext": "none", "vbr": 2079.033, "abr": 0.0, "format": "22 - 1280x720 (720p)", "http_headers": {"User-Agent": "Mozilla/5.0 (Windows NT 10.0; Win64; x64) AppleWebKit/537.36 (KHTML, like Gecko) Chrome/71.0.3569.1 Safari/537.36", "Accept-Charset": "ISO-8859-1,utf-8;q=0.7,*;q=0.7", "Accept": "text/html,application/xhtml+xml,application/xml;q=0.9,*/*;q=0.8", "Accept-Encoding": "gzip, deflate", "Accept-Language": "en-us,en;q=0.5"}}, {"filesize": 340826393, "format_id": "247", "format_note": "720p", "fps": 30, "height": 720, "quality": 8, "tbr": 1535.571, "url": "https://rr1---sn-ab5sznle.googlevideo.com/videoplayback?expire=1641438830&ei=DgrWYYHwB4_08gTsyoGQCw&ip=68.70.26.44&id=o-AKihYnUGZNK-nm3zs0lt1HySprvzOQ4sdtJqX4G59nVj&itag=247&source=youtube&requiressl=yes&mh=xl&mm=31%2C29&mn=sn-ab5sznle%2Csn-ab5l6ndy&ms=au%2Crdu&mv=m&mvi=1&pl=20&initcwndbps=1412500&vprv=1&mime=video%2Fwebm&gir=yes&clen=340826393&dur=1775.633&lmt=1457587611158144&mt=1641416931&fvip=1&keepalive=yes&fexp=24001373%2C24007246&c=ANDROID&sparams=expire%2Cei%2Cip%2Cid%2Citag%2Csource%2Crequiressl%2Cvprv%2Cmime%2Cgir%2Cclen%2Cdur%2Clmt&sig=AOq0QJ8wRQIgHbFHqSKPeE8UjACa_v44mWMBRgLk9DdpNKZgsoqZXy8CIQCnXFeCpm1VYb9iaBcIoK208o1KVda09kmUTSqsssRBSg%3D%3D&lsparams=mh%2Cmm%2Cmn%2Cms%2Cmv%2Cmvi%2Cpl%2Cinitcwndbps&lsig=AG3C_xAwRQIhAOYXo-_JVdAk1vvtiXEwRyRvbt1SvR7lGKXBJa-zhdMWAiASE0jgowU1hWlQ9BmgNeSAfBZFvS7Rz7mflCGSo9sZrw%3D%3D", "width": 1280, "language": "", "language_preference": -1, "ext": "webm", "vcodec": "vp9", "acodec": "none", "vbr": 1535.571, "downloader_options": {"http_chunk_size": 10485760}, "container": "webm_dash", "protocol": "https", "video_ext": "webm", "audio_ext": "none", "format": "247 - 1280x720 (720p)", "http_headers": {"User-Agent": "Mozilla/5.0 (Windows NT 10.0; Win64; x64) AppleWebKit/537.36 (KHTML, like Gecko) Chrome/71.0.3569.1 Safari/537.36", "Accept-Charset": "ISO-8859-1,utf-8;q=0.7,*;q=0.7", "Accept": "text/html,application/xhtml+xml,application/xml;q=0.9,*/*;q=0.8", "Accept-Encoding": "gzip, deflate", "Accept-Language": "en-us,en;q=0.5"}}], "thumbnails": [{"url": "https://i.ytimg.com/vi/k2rCn74gnAs/3.jpg", "preference": -37, "id": "0"}, {"url": "https://i.ytimg.com/vi_webp/k2rCn74gnAs/3.webp", "preference": -36, "id": "1"}, {"url": "https://i.ytimg.com/vi/k2rCn74gnAs/2.jpg", "preference": -35, "id": "2"}, {"url": "https://i.ytimg.com/vi_webp/k2rCn74gnAs/2.webp", "preference": -34, "id": "3"}, {"url": "https://i.ytimg.com/vi/k2rCn74gnAs/1.jpg", "preference": -33, "id": "4"}, {"url": "https://i.ytimg.com/vi_webp/k2rCn74gnAs/1.webp", "preference": -32, "id": "5"}, {"url": "https://i.ytimg.com/vi/k2rCn74gnAs/default.jpg", "preference": -31, "id": "6"}, {"url": "https://i.ytimg.com/vi_webp/k2rCn74gnAs/default.webp", "height": 90, "width": 120, "preference": -30, "id": "7", "resolution": "120x90"}, {"url": "https://i.ytimg.com/vi/k2rCn74gnAs/mq3.jpg", "preference": -29, "id": "8"}, {"url": "https://i.ytimg.com/vi_webp/k2rCn74gnAs/mq3.webp", "preference": -28, "id": "9"}, {"url": "https://i.ytimg.com/vi/k2rCn74gnAs/mq2.jpg", "preference": -27, "id": "10"}, {"url": "https://i.ytimg.com/vi_webp/k2rCn74gnAs/mq2.webp", "preference": -26, "id": "11"}, {"url": "https://i.ytimg.com/vi/k2rCn74gnAs/mq1.jpg", "preference": -25, "id": "12"}, {"url": "https://i.ytimg.com/vi_webp/k2rCn74gnAs/mq1.webp", "preference": -24, "id": "13"}, {"url": "https://i.ytimg.com/vi/k2rCn74gnAs/mqdefault.jpg", "preference": -23, "id": "14"}, {"url": "https://i.ytimg.com/vi_webp/k2rCn74gnAs/mqdefault.webp", "height": 180, "width": 320, "preference": -22, "id": "15", "resolution": "320x180"}, {"url": "https://i.ytimg.com/vi/k2rCn74gnAs/0.jpg", "preference": -21, "id": "16"}, {"url": "https://i.ytimg.com/vi_webp/k2rCn74gnAs/0.webp", "preference": -20, "id": "17"}, {"url": "https://i.ytimg.com/vi/k2rCn74gnAs/hq3.jpg", "preference": -19, "id": "18"}, {"url": "https://i.ytimg.com/vi_webp/k2rCn74gnAs/hq3.webp", "preference": -18, "id": "19"}, {"url": "https://i.ytimg.com/vi/k2rCn74gnAs/hq2.jpg", "preference": -17, "id": "20"}, {"url": "https://i.ytimg.com/vi_webp/k2rCn74gnAs/hq2.webp", "preference": -16, "id": "21"}, {"url": "https://i.ytimg.com/vi/k2rCn74gnAs/hq1.jpg", "preference": -15, "id": "22"}, {"url": "https://i.ytimg.com/vi_webp/k2rCn74gnAs/hq1.webp", "preference": -14, "id": "23"}, {"url": "https://i.ytimg.com/vi/k2rCn74gnAs/hqdefault.jpg", "preference": -13, "id": "24"}, {"url": "https://i.ytimg.com/vi/k2rCn74gnAs/hqdefault.jpg?sqp=-oaymwEbCKgBEF5IVfKriqkDDggBFQAAiEIYAXABwAEG&rs=AOn4CLA5D3t2r5UaDTVRgKhaO9D1pPhPEQ", "height": 94, "width": 168, "preference": -13, "id": "25", "resolution": "168x94"}, {"url": "https://i.ytimg.com/vi/k2rCn74gnAs/hqdefault.jpg?sqp=-oaymwEbCMQBEG5IVfKriqkDDggBFQAAiEIYAXABwAEG&rs=AOn4CLD1iR0v7R925pPUfiOJ7DK1V0hCaQ", "height": 110, "width": 196, "preference": -13, "id": "26", "resolution": "196x110"}, {"url": "https://i.ytimg.com/vi/k2rCn74gnAs/hqdefault.jpg?sqp=-oaymwEcCPYBEIoBSFXyq4qpAw4IARUAAIhCGAFwAcABBg==&rs=AOn4CLCQILWpLdomLRkCx0Vr0rHgqVsbNA", "height": 138, "width": 246, "preference": -13, "id": "27", "resolution": "246x138"}, {"url": "https://i.ytimg.com/vi/k2rCn74gnAs/hqdefault.jpg?sqp=-oaymwEcCNACELwBSFXyq4qpAw4IARUAAIhCGAFwAcABBg==&rs=AOn4CLCyQLIPDgCJcw5Hqd8ATHHIuKiPQw", "height": 188, "width": 336, "preference": -13, "id": "28", "resolution": "336x188"}, {"url": "https://i.ytimg.com/vi_webp/k2rCn74gnAs/hqdefault.webp", "height": 360, "width": 480, "preference": -12, "id": "29", "resolution": "480x360"}, {"url": "https://i.ytimg.com/vi/k2rCn74gnAs/sd3.jpg", "preference": -11, "id": "30"}, {"url": "https://i.ytimg.com/vi_webp/k2rCn74gnAs/sd3.webp", "preference": -10, "id": "31"}, {"url": "https://i.ytimg.com/vi/k2rCn74gnAs/sd2.jpg", "preference": -9, "id": "32"}, {"url": "https://i.ytimg.com/vi_webp/k2rCn74gnAs/sd2.webp", "preference": -8, "id": "33"}, {"url": "https://i.ytimg.com/vi/k2rCn74gnAs/sd1.jpg", "preference": -7, "id": "34"}, {"url": "https://i.ytimg.com/vi_webp/k2rCn74gnAs/sd1.webp", "preference": -6, "id": "35"}, {"url": "https://i.ytimg.com/vi/k2rCn74gnAs/sddefault.jpg", "preference": -5, "id": "36"}, {"url": "https://i.ytimg.com/vi_webp/k2rCn74gnAs/sddefault.webp", "height": 480, "width": 640, "preference": -4, "id": "37", "resolution": "640x480"}, {"url": "https://i.ytimg.com/vi/k2rCn74gnAs/hq720.jpg", "preference": -3, "id": "38"}, {"url": "https://i.ytimg.com/vi_webp/k2rCn74gnAs/hq720.webp", "preference": -2, "id": "39"}, {"url": "https://i.ytimg.com/vi/k2rCn74gnAs/maxresdefault.jpg", "height": 720, "width": 1280, "preference": -1, "id": "40", "resolution": "1280x720"}, {"url": "https://i.ytimg.com/vi_webp/k2rCn74gnAs/maxresdefault.webp", "height": 1080, "width": 1920, "preference": 0, "id": "41", "resolution": "1920x1080"}], "description": "Ark Survival Evolved. In this episode the Horton crew focuses on getting well established on the server with more tames, more buildings, and more raids.\n\nTydeesigns: https://www.youtube.com/user/tydeesigns\nDarkphan: https://www.youtube.com/user/darkphanlp\nPutzee: https://www.youtube.com/user/PutzeePlayz\n\nTwitter: http://www.twitter.com/EthoLP\nTwitchTV: http://www.twitch.tv/ethotv/videos", "upload_date": "20160310", "uploader": "EthosLab", "uploader_id": "EthosLab", "uploader_url": "http://www.youtube.com/user/EthosLab", "channel_id": "UCFKDEp9si4RmHFWJW1vYsMA", "channel_url": "https://www.youtube.com/channel/UCFKDEp9si4RmHFWJW1vYsMA", "duration": 1776, "view_count": 162520, "age_limit": 0, "webpage_url": "https://www.youtube.com/watch?v=k2rCn74gnAs", "categories": ["Gaming"], "tags": ["Ark", "Ark Survival", "Ark Survival Evolved", "Ark Survival Evolved Gameplay", "Ark Survival Evolved Taming", "Ark Survival Evolved PVP", "Ark Survival Evolved Raiding", "Ark Gameplay", "etho", "Ark Building", "Gameplay", "Valhalla Map", "Gaming", "Dinosaur"], "playable_in_embed": true, "is_live": false, "was_live": false, "live_status": "not_live", "like_count": 5497, "channel": "EthosLab", "availability": "public", "webpage_url_basename": "watch", "extractor": "youtube", "extractor_key": "Youtube", "n_entries": 5, "playlist_index": 4, "playlist": "ARK: Survival Evolved PVP", "playlist_id": "PLaOY2J77tsfvFXn288CUYwPSgPqplNQfm", "playlist_title": "ARK: Survival Evolved PVP", "playlist_uploader": "Playlists", "playlist_uploader_id": "UC8myOLsYDH1vqYtjFhimrqQ", "thumbnail": "https://i.ytimg.com/vi_webp/k2rCn74gnAs/maxresdefault.webp", "display_id": "k2rCn74gnAs", "asr": 44100, "format_id": "22", "format_note": "720p", "fps": 30, "height": 720, "quality": 8, "tbr": 2079.033, "url": "https://rr1---sn-ab5sznle.googlevideo.com/videoplayback?expire=1641438830&ei=DgrWYYHwB4_08gTsyoGQCw&ip=68.70.26.44&id=o-AKihYnUGZNK-nm3zs0lt1HySprvzOQ4sdtJqX4G59nVj&itag=22&source=youtube&requiressl=yes&mh=xl&mm=31%2C29&mn=sn-ab5sznle%2Csn-ab5l6ndy&ms=au%2Crdu&mv=m&mvi=1&pl=20&initcwndbps=1412500&vprv=1&mime=video%2Fmp4&cnr=14&ratebypass=yes&dur=1775.722&lmt=1472390431796707&mt=1641416931&fvip=1&fexp=24001373%2C24007246&c=ANDROID&sparams=expire%2Cei%2Cip%2Cid%2Citag%2Csource%2Crequiressl%2Cvprv%2Cmime%2Ccnr%2Cratebypass%2Cdur%2Clmt&sig=AOq0QJ8wRgIhAI9hPkFw3KqEjk0yQfC11zvtJ09vNN5dXKtSHppN-h-IAiEArKrspTswZUO0e0Kd30xi-jRm_3hktsJfWe8i7AQ3bhw%3D&lsparams=mh%2Cmm%2Cmn%2Cms%2Cmv%2Cmvi%2Cpl%2Cinitcwndbps&lsig=AG3C_xAwRQIhAOYXo-_JVdAk1vvtiXEwRyRvbt1SvR7lGKXBJa-zhdMWAiASE0jgowU1hWlQ9BmgNeSAfBZFvS7Rz7mflCGSo9sZrw%3D%3D", "width": 1280, "language": "", "language_preference": -1, "ext": "mp4", "vcodec": "avc1.64001F", "acodec": "mp4a.40.2", "protocol": "https", "video_ext": "mp4", "audio_ext": "none", "vbr": 2079.033, "abr": 0.0, "format": "22 - 1280x720 (720p)", "http_headers": {"User-Agent": "Mozilla/5.0 (Windows NT 10.0; Win64; x64) AppleWebKit/537.36 (KHTML, like Gecko) Chrome/71.0.3569.1 Safari/537.36", "Accept-Charset": "ISO-8859-1,utf-8;q=0.7,*;q=0.7", "Accept": "text/html,application/xhtml+xml,application/xml;q=0.9,*/*;q=0.8", "Accept-Encoding": "gzip, deflate", "Accept-Language": "en-us,en;q=0.5"}, "fulltitle": "ARK Survival Evolved PVP #4: Flight For All", "epoch": 1641417231}